[
  {
    "shape_pt_sequence" : 0,
    "shape_id" : "1B223DB9-78C8-4A42-8F3E-62EC9CB60AA7",
    "shape_pt_lon" : 28.978280000000012,
    "shape_pt_lat" : 41.014986999999984
  },
  {
    "shape_pt_sequence" : 1,
    "shape_id" : "1B223DB9-78C8-4A42-8F3E-62EC9CB60AA7",
    "shape_pt_lon" : 28.983147000000002,
    "shape_pt_lat" : 41.015971999999998
  },
  {
    "shape_pt_sequence" : 2,
    "shape_id" : "1B223DB9-78C8-4A42-8F3E-62EC9CB60AA7",
    "shape_pt_lon" : 28.986563999999987,
    "shape_pt_lat" : 41.015199999999993
  },
  {
    "shape_pt_sequence" : 3,
    "shape_id" : "1B223DB9-78C8-4A42-8F3E-62EC9CB60AA7",
    "shape_pt_lon" : 28.982299000000012,
    "shape_pt_lat" : 41.005148999999996
  },
  {
    "shape_pt_sequence" : 4,
    "shape_id" : "1B223DB9-78C8-4A42-8F3E-62EC9CB60AA7",
    "shape_pt_lon" : 28.973220000000026,
    "shape_pt_lat" : 41.002451999999998
  },
  {
    "shape_pt_sequence" : 5,
    "shape_id" : "1B223DB9-78C8-4A42-8F3E-62EC9CB60AA7",
    "shape_pt_lon" : 28.964614000000012,
    "shape_pt_lat" : 41.003270999999998
  },
  {
    "shape_pt_sequence" : 6,
    "shape_id" : "1B223DB9-78C8-4A42-8F3E-62EC9CB60AA7",
    "shape_pt_lon" : 28.952219000000042,
    "shape_pt_lat" : 41.004748999999997
  },
  {
    "shape_pt_sequence" : 7,
    "shape_id" : "1B223DB9-78C8-4A42-8F3E-62EC9CB60AA7",
    "shape_pt_lon" : 28.938037000000008,
    "shape_pt_lat" : 41.002304000000002
  },
  {
    "shape_pt_sequence" : 8,
    "shape_id" : "1B223DB9-78C8-4A42-8F3E-62EC9CB60AA7",
    "shape_pt_lon" : 28.931640000000044,
    "shape_pt_lat" : 40.997702999999987
  },
  {
    "shape_pt_sequence" : 9,
    "shape_id" : "1B223DB9-78C8-4A42-8F3E-62EC9CB60AA7",
    "shape_pt_lon" : 28.928131000000036,
    "shape_pt_lat" : 40.994205000000001
  },
  {
    "shape_pt_sequence" : 10,
    "shape_id" : "1B223DB9-78C8-4A42-8F3E-62EC9CB60AA7",
    "shape_pt_lon" : 28.922294000000022,
    "shape_pt_lat" : 40.991687999999989
  },
  {
    "shape_pt_sequence" : 11,
    "shape_id" : "1B223DB9-78C8-4A42-8F3E-62EC9CB60AA7",
    "shape_pt_lon" : 28.916699999999992,
    "shape_pt_lat" : 40.992606000000009
  },
  {
    "shape_pt_sequence" : 12,
    "shape_id" : "1B223DB9-78C8-4A42-8F3E-62EC9CB60AA7",
    "shape_pt_lon" : 28.911572000000035,
    "shape_pt_lat" : 40.991865999999995
  },
  {
    "shape_pt_sequence" : 13,
    "shape_id" : "1B223DB9-78C8-4A42-8F3E-62EC9CB60AA7",
    "shape_pt_lon" : 28.903989999999993,
    "shape_pt_lat" : 40.984610999999994
  },
  {
    "shape_pt_sequence" : 14,
    "shape_id" : "1B223DB9-78C8-4A42-8F3E-62EC9CB60AA7",
    "shape_pt_lon" : 28.892954000000032,
    "shape_pt_lat" : 40.982521999999996
  },
  {
    "shape_pt_sequence" : 15,
    "shape_id" : "1B223DB9-78C8-4A42-8F3E-62EC9CB60AA7",
    "shape_pt_lon" : 28.875505000000004,
    "shape_pt_lat" : 40.980775000000001
  },
  {
    "shape_pt_sequence" : 16,
    "shape_id" : "1B223DB9-78C8-4A42-8F3E-62EC9CB60AA7",
    "shape_pt_lon" : 28.85865000000004,
    "shape_pt_lat" : 40.980156999999991
  },
  {
    "shape_pt_sequence" : 17,
    "shape_id" : "1B223DB9-78C8-4A42-8F3E-62EC9CB60AA7",
    "shape_pt_lon" : 28.848973999999998,
    "shape_pt_lat" : 40.979504999999996
  },
  {
    "shape_pt_sequence" : 18,
    "shape_id" : "1B223DB9-78C8-4A42-8F3E-62EC9CB60AA7",
    "shape_pt_lon" : 28.843330000000037,
    "shape_pt_lat" : 40.975796000000003
  },
  {
    "shape_pt_sequence" : 19,
    "shape_id" : "1B223DB9-78C8-4A42-8F3E-62EC9CB60AA7",
    "shape_pt_lon" : 28.835916999999995,
    "shape_pt_lat" : 40.964373999999999
  },
  {
    "shape_pt_sequence" : 20,
    "shape_id" : "1B223DB9-78C8-4A42-8F3E-62EC9CB60AA7",
    "shape_pt_lon" : 28.827248000000026,
    "shape_pt_lat" : 40.962417999999992
  },
  {
    "shape_pt_sequence" : 21,
    "shape_id" : "1B223DB9-78C8-4A42-8F3E-62EC9CB60AA7",
    "shape_pt_lon" : 28.801541999999984,
    "shape_pt_lat" : 40.964674000000009
  },
  {
    "shape_pt_sequence" : 22,
    "shape_id" : "1B223DB9-78C8-4A42-8F3E-62EC9CB60AA7",
    "shape_pt_lon" : 28.794621000000006,
    "shape_pt_lat" : 40.970178999999995
  },
  {
    "shape_pt_sequence" : 23,
    "shape_id" : "1B223DB9-78C8-4A42-8F3E-62EC9CB60AA7",
    "shape_pt_lon" : 28.783724000000035,
    "shape_pt_lat" : 40.974164000000002
  },
  {
    "shape_pt_sequence" : 24,
    "shape_id" : "1B223DB9-78C8-4A42-8F3E-62EC9CB60AA7",
    "shape_pt_lon" : 28.775567000000024,
    "shape_pt_lat" : 40.977986999999992
  },
  {
    "shape_pt_sequence" : 25,
    "shape_id" : "1B223DB9-78C8-4A42-8F3E-62EC9CB60AA7",
    "shape_pt_lon" : 28.776231999999993,
    "shape_pt_lat" : 40.981884999999984
  },
  {
    "shape_pt_sequence" : 26,
    "shape_id" : "1B223DB9-78C8-4A42-8F3E-62EC9CB60AA7",
    "shape_pt_lon" : 28.772796,
    "shape_pt_lat" : 40.989240999999993
  },
  {
    "shape_pt_sequence" : 27,
    "shape_id" : "1B223DB9-78C8-4A42-8F3E-62EC9CB60AA7",
    "shape_pt_lon" : 28.768009000000006,
    "shape_pt_lat" : 40.995611999999994
  },
  {
    "shape_pt_sequence" : 28,
    "shape_id" : "1B223DB9-78C8-4A42-8F3E-62EC9CB60AA7",
    "shape_pt_lon" : 28.769483000000008,
    "shape_pt_lat" : 41.002084999999987
  },
  {
    "shape_pt_sequence" : 29,
    "shape_id" : "1B223DB9-78C8-4A42-8F3E-62EC9CB60AA7",
    "shape_pt_lon" : 28.77432300000001,
    "shape_pt_lat" : 41.006847999999984
  },
  {
    "shape_pt_sequence" : 30,
    "shape_id" : "1B223DB9-78C8-4A42-8F3E-62EC9CB60AA7",
    "shape_pt_lon" : 28.773502000000008,
    "shape_pt_lat" : 41.010476999999995
  },
  {
    "shape_pt_sequence" : 31,
    "shape_id" : "1B223DB9-78C8-4A42-8F3E-62EC9CB60AA7",
    "shape_pt_lon" : 28.768577999999991,
    "shape_pt_lat" : 41.012217999999997
  },
  {
    "shape_pt_sequence" : 32,
    "shape_id" : "1B223DB9-78C8-4A42-8F3E-62EC9CB60AA7",
    "shape_pt_lon" : 28.766643999999957,
    "shape_pt_lat" : 41.015881999999998
  },
  {
    "shape_pt_sequence" : 33,
    "shape_id" : "1B223DB9-78C8-4A42-8F3E-62EC9CB60AA7",
    "shape_pt_lon" : 28.766035999999986,
    "shape_pt_lat" : 41.024845999999982
  },
  {
    "shape_pt_sequence" : 34,
    "shape_id" : "1B223DB9-78C8-4A42-8F3E-62EC9CB60AA7",
    "shape_pt_lon" : 28.763553000000002,
    "shape_pt_lat" : 41.034091000000004
  },
  {
    "shape_pt_sequence" : 35,
    "shape_id" : "1B223DB9-78C8-4A42-8F3E-62EC9CB60AA7",
    "shape_pt_lon" : 28.759105000000005,
    "shape_pt_lat" : 41.040609999999987
  },
  {
    "shape_pt_sequence" : 36,
    "shape_id" : "1B223DB9-78C8-4A42-8F3E-62EC9CB60AA7",
    "shape_pt_lon" : 28.751060999999993,
    "shape_pt_lat" : 41.044032999999985
  },
  {
    "shape_pt_sequence" : 37,
    "shape_id" : "1B223DB9-78C8-4A42-8F3E-62EC9CB60AA7",
    "shape_pt_lon" : 28.747731000000016,
    "shape_pt_lat" : 41.048327999999984
  },
  {
    "shape_pt_sequence" : 38,
    "shape_id" : "1B223DB9-78C8-4A42-8F3E-62EC9CB60AA7",
    "shape_pt_lon" : 28.748909999999995,
    "shape_pt_lat" : 41.054155000000002
  },
  {
    "shape_pt_sequence" : 39,
    "shape_id" : "1B223DB9-78C8-4A42-8F3E-62EC9CB60AA7",
    "shape_pt_lon" : 28.746161000000001,
    "shape_pt_lat" : 41.058842999999989
  },
  {
    "shape_pt_sequence" : 40,
    "shape_id" : "1B223DB9-78C8-4A42-8F3E-62EC9CB60AA7",
    "shape_pt_lon" : 28.739233000000013,
    "shape_pt_lat" : 41.060372999999998
  },
  {
    "shape_pt_sequence" : 41,
    "shape_id" : "1B223DB9-78C8-4A42-8F3E-62EC9CB60AA7",
    "shape_pt_lon" : 28.733353000000022,
    "shape_pt_lat" : 41.057189999999984
  },
  {
    "shape_pt_sequence" : 42,
    "shape_id" : "1B223DB9-78C8-4A42-8F3E-62EC9CB60AA7",
    "shape_pt_lon" : 28.731180999999992,
    "shape_pt_lat" : 41.052051000000006
  },
  {
    "shape_pt_sequence" : 43,
    "shape_id" : "1B223DB9-78C8-4A42-8F3E-62EC9CB60AA7",
    "shape_pt_lon" : 28.724830999999966,
    "shape_pt_lat" : 41.048477999999996
  },
  {
    "shape_pt_sequence" : 44,
    "shape_id" : "1B223DB9-78C8-4A42-8F3E-62EC9CB60AA7",
    "shape_pt_lon" : 28.717627999999991,
    "shape_pt_lat" : 41.049432999999993
  },
  {
    "shape_pt_sequence" : 45,
    "shape_id" : "1B223DB9-78C8-4A42-8F3E-62EC9CB60AA7",
    "shape_pt_lon" : 28.701134999999994,
    "shape_pt_lat" : 41.059622999999988
  },
  {
    "shape_pt_sequence" : 46,
    "shape_id" : "1B223DB9-78C8-4A42-8F3E-62EC9CB60AA7",
    "shape_pt_lon" : 28.697818000000012,
    "shape_pt_lat" : 41.06545400000001
  },
  {
    "shape_pt_sequence" : 47,
    "shape_id" : "1B223DB9-78C8-4A42-8F3E-62EC9CB60AA7",
    "shape_pt_lon" : 28.69176600000003,
    "shape_pt_lat" : 41.072822999999993
  },
  {
    "shape_pt_sequence" : 48,
    "shape_id" : "1B223DB9-78C8-4A42-8F3E-62EC9CB60AA7",
    "shape_pt_lon" : 28.686252999999994,
    "shape_pt_lat" : 41.078479999999999
  },
  {
    "shape_pt_sequence" : 49,
    "shape_id" : "1B223DB9-78C8-4A42-8F3E-62EC9CB60AA7",
    "shape_pt_lon" : 28.675916000000029,
    "shape_pt_lat" : 41.086852999999991
  },
  {
    "shape_pt_sequence" : 50,
    "shape_id" : "1B223DB9-78C8-4A42-8F3E-62EC9CB60AA7",
    "shape_pt_lon" : 28.667915999999991,
    "shape_pt_lat" : 41.096378000000009
  },
  {
    "shape_pt_sequence" : 51,
    "shape_id" : "1B223DB9-78C8-4A42-8F3E-62EC9CB60AA7",
    "shape_pt_lon" : 28.662295000000029,
    "shape_pt_lat" : 41.102496999999993
  },
  {
    "shape_pt_sequence" : 52,
    "shape_id" : "1B223DB9-78C8-4A42-8F3E-62EC9CB60AA7",
    "shape_pt_lon" : 28.652056000000016,
    "shape_pt_lat" : 41.109319999999997
  },
  {
    "shape_pt_sequence" : 53,
    "shape_id" : "1B223DB9-78C8-4A42-8F3E-62EC9CB60AA7",
    "shape_pt_lon" : 28.644425000000041,
    "shape_pt_lat" : 41.11368499999999
  },
  {
    "shape_pt_sequence" : 54,
    "shape_id" : "1B223DB9-78C8-4A42-8F3E-62EC9CB60AA7",
    "shape_pt_lon" : 28.639640000000014,
    "shape_pt_lat" : 41.123122000000002
  },
  {
    "shape_pt_sequence" : 55,
    "shape_id" : "1B223DB9-78C8-4A42-8F3E-62EC9CB60AA7",
    "shape_pt_lon" : 28.633132999999987,
    "shape_pt_lat" : 41.129004999999992
  },
  {
    "shape_pt_sequence" : 56,
    "shape_id" : "1B223DB9-78C8-4A42-8F3E-62EC9CB60AA7",
    "shape_pt_lon" : 28.607893999999987,
    "shape_pt_lat" : 41.132573999999991
  },
  {
    "shape_pt_sequence" : 57,
    "shape_id" : "1B223DB9-78C8-4A42-8F3E-62EC9CB60AA7",
    "shape_pt_lon" : 28.596961999999991,
    "shape_pt_lat" : 41.137853999999983
  },
  {
    "shape_pt_sequence" : 58,
    "shape_id" : "1B223DB9-78C8-4A42-8F3E-62EC9CB60AA7",
    "shape_pt_lon" : 28.579461000000038,
    "shape_pt_lat" : 41.134955999999995
  },
  {
    "shape_pt_sequence" : 59,
    "shape_id" : "1B223DB9-78C8-4A42-8F3E-62EC9CB60AA7",
    "shape_pt_lon" : 28.563458000000026,
    "shape_pt_lat" : 41.127190999999996
  },
  {
    "shape_pt_sequence" : 60,
    "shape_id" : "1B223DB9-78C8-4A42-8F3E-62EC9CB60AA7",
    "shape_pt_lon" : 28.550855000000013,
    "shape_pt_lat" : 41.128729
  },
  {
    "shape_pt_sequence" : 61,
    "shape_id" : "1B223DB9-78C8-4A42-8F3E-62EC9CB60AA7",
    "shape_pt_lon" : 28.540286000000009,
    "shape_pt_lat" : 41.134655999999993
  },
  {
    "shape_pt_sequence" : 62,
    "shape_id" : "1B223DB9-78C8-4A42-8F3E-62EC9CB60AA7",
    "shape_pt_lon" : 28.526633000000004,
    "shape_pt_lat" : 41.137627999999992
  },
  {
    "shape_pt_sequence" : 63,
    "shape_id" : "1B223DB9-78C8-4A42-8F3E-62EC9CB60AA7",
    "shape_pt_lon" : 28.493626000000006,
    "shape_pt_lat" : 41.143653000000015
  },
  {
    "shape_pt_sequence" : 64,
    "shape_id" : "1B223DB9-78C8-4A42-8F3E-62EC9CB60AA7",
    "shape_pt_lon" : 28.48225800000003,
    "shape_pt_lat" : 41.149193000000004
  },
  {
    "shape_pt_sequence" : 65,
    "shape_id" : "1B223DB9-78C8-4A42-8F3E-62EC9CB60AA7",
    "shape_pt_lon" : 28.472656000000001,
    "shape_pt_lat" : 41.156560000000006
  },
  {
    "shape_pt_sequence" : 66,
    "shape_id" : "1B223DB9-78C8-4A42-8F3E-62EC9CB60AA7",
    "shape_pt_lon" : 28.461390000000023,
    "shape_pt_lat" : 41.167977999999998
  },
  {
    "shape_pt_sequence" : 67,
    "shape_id" : "1B223DB9-78C8-4A42-8F3E-62EC9CB60AA7",
    "shape_pt_lon" : 28.442371000000037,
    "shape_pt_lat" : 41.184517999999997
  },
  {
    "shape_pt_sequence" : 68,
    "shape_id" : "1B223DB9-78C8-4A42-8F3E-62EC9CB60AA7",
    "shape_pt_lon" : 28.42727099999999,
    "shape_pt_lat" : 41.189908000000003
  },
  {
    "shape_pt_sequence" : 69,
    "shape_id" : "1B223DB9-78C8-4A42-8F3E-62EC9CB60AA7",
    "shape_pt_lon" : 28.41604300000003,
    "shape_pt_lat" : 41.190300000000008
  },
  {
    "shape_pt_sequence" : 70,
    "shape_id" : "1B223DB9-78C8-4A42-8F3E-62EC9CB60AA7",
    "shape_pt_lon" : 28.406708000000037,
    "shape_pt_lat" : 41.189712999999983
  },
  {
    "shape_pt_sequence" : 71,
    "shape_id" : "1B223DB9-78C8-4A42-8F3E-62EC9CB60AA7",
    "shape_pt_lon" : 28.400385,
    "shape_pt_lat" : 41.193230000000014
  },
  {
    "shape_pt_sequence" : 72,
    "shape_id" : "1B223DB9-78C8-4A42-8F3E-62EC9CB60AA7",
    "shape_pt_lon" : 28.392515000000003,
    "shape_pt_lat" : 41.201575999999996
  },
  {
    "shape_pt_sequence" : 73,
    "shape_id" : "1B223DB9-78C8-4A42-8F3E-62EC9CB60AA7",
    "shape_pt_lon" : 28.372527999999988,
    "shape_pt_lat" : 41.209784999999982
  },
  {
    "shape_pt_sequence" : 74,
    "shape_id" : "1B223DB9-78C8-4A42-8F3E-62EC9CB60AA7",
    "shape_pt_lon" : 28.362966999999998,
    "shape_pt_lat" : 41.217027999999992
  },
  {
    "shape_pt_sequence" : 75,
    "shape_id" : "1B223DB9-78C8-4A42-8F3E-62EC9CB60AA7",
    "shape_pt_lon" : 28.35728499999999,
    "shape_pt_lat" : 41.218724999999999
  },
  {
    "shape_pt_sequence" : 76,
    "shape_id" : "1B223DB9-78C8-4A42-8F3E-62EC9CB60AA7",
    "shape_pt_lon" : 28.339008000000035,
    "shape_pt_lat" : 41.217733000000003
  },
  {
    "shape_pt_sequence" : 77,
    "shape_id" : "1B223DB9-78C8-4A42-8F3E-62EC9CB60AA7",
    "shape_pt_lon" : 28.325195000000008,
    "shape_pt_lat" : 41.213188000000002
  },
  {
    "shape_pt_sequence" : 78,
    "shape_id" : "1B223DB9-78C8-4A42-8F3E-62EC9CB60AA7",
    "shape_pt_lon" : 28.318930999999992,
    "shape_pt_lat" : 41.210682999999989
  },
  {
    "shape_pt_sequence" : 79,
    "shape_id" : "1B223DB9-78C8-4A42-8F3E-62EC9CB60AA7",
    "shape_pt_lon" : 28.313095000000033,
    "shape_pt_lat" : 41.209105000000008
  },
  {
    "shape_pt_sequence" : 80,
    "shape_id" : "1B223DB9-78C8-4A42-8F3E-62EC9CB60AA7",
    "shape_pt_lon" : 28.307906000000003,
    "shape_pt_lat" : 41.204700999999993
  },
  {
    "shape_pt_sequence" : 81,
    "shape_id" : "1B223DB9-78C8-4A42-8F3E-62EC9CB60AA7",
    "shape_pt_lon" : 28.300878000000012,
    "shape_pt_lat" : 41.199970999999991
  },
  {
    "shape_pt_sequence" : 82,
    "shape_id" : "1B223DB9-78C8-4A42-8F3E-62EC9CB60AA7",
    "shape_pt_lon" : 28.295805000000001,
    "shape_pt_lat" : 41.197672999999995
  },
  {
    "shape_pt_sequence" : 83,
    "shape_id" : "1B223DB9-78C8-4A42-8F3E-62EC9CB60AA7",
    "shape_pt_lon" : 28.287588,
    "shape_pt_lat" : 41.192510999999996
  },
  {
    "shape_pt_sequence" : 84,
    "shape_id" : "1B223DB9-78C8-4A42-8F3E-62EC9CB60AA7",
    "shape_pt_lon" : 28.284875000000028,
    "shape_pt_lat" : 41.187729999999988
  },
  {
    "shape_pt_sequence" : 85,
    "shape_id" : "1B223DB9-78C8-4A42-8F3E-62EC9CB60AA7",
    "shape_pt_lon" : 28.280706000000038,
    "shape_pt_lat" : 41.186977999999996
  },
  {
    "shape_pt_sequence" : 86,
    "shape_id" : "1B223DB9-78C8-4A42-8F3E-62EC9CB60AA7",
    "shape_pt_lon" : 28.278491000000031,
    "shape_pt_lat" : 41.189797999999996
  },
  {
    "shape_pt_sequence" : 87,
    "shape_id" : "1B223DB9-78C8-4A42-8F3E-62EC9CB60AA7",
    "shape_pt_lon" : 28.279865999999998,
    "shape_pt_lat" : 41.193449999999991
  },
  {
    "shape_pt_sequence" : 88,
    "shape_id" : "1B223DB9-78C8-4A42-8F3E-62EC9CB60AA7",
    "shape_pt_lon" : 28.276305000000008,
    "shape_pt_lat" : 41.196970999999991
  },
  {
    "shape_pt_sequence" : 89,
    "shape_id" : "1B223DB9-78C8-4A42-8F3E-62EC9CB60AA7",
    "shape_pt_lon" : 28.273686000000026,
    "shape_pt_lat" : 41.199920000000006
  },
  {
    "shape_pt_sequence" : 90,
    "shape_id" : "1B223DB9-78C8-4A42-8F3E-62EC9CB60AA7",
    "shape_pt_lon" : 28.265691000000004,
    "shape_pt_lat" : 41.203929999999993
  },
  {
    "shape_pt_sequence" : 91,
    "shape_id" : "1B223DB9-78C8-4A42-8F3E-62EC9CB60AA7",
    "shape_pt_lon" : 28.263407999999998,
    "shape_pt_lat" : 41.210950000000004
  },
  {
    "shape_pt_sequence" : 92,
    "shape_id" : "1B223DB9-78C8-4A42-8F3E-62EC9CB60AA7",
    "shape_pt_lon" : 28.263947999999999,
    "shape_pt_lat" : 41.216255999999994
  },
  {
    "shape_pt_sequence" : 93,
    "shape_id" : "1B223DB9-78C8-4A42-8F3E-62EC9CB60AA7",
    "shape_pt_lon" : 28.266263000000009,
    "shape_pt_lat" : 41.220709999999983
  },
  {
    "shape_pt_sequence" : 94,
    "shape_id" : "1B223DB9-78C8-4A42-8F3E-62EC9CB60AA7",
    "shape_pt_lon" : 28.267655000000019,
    "shape_pt_lat" : 41.224874999999997
  },
  {
    "shape_pt_sequence" : 95,
    "shape_id" : "1B223DB9-78C8-4A42-8F3E-62EC9CB60AA7",
    "shape_pt_lon" : 28.270666000000006,
    "shape_pt_lat" : 41.234445999999998
  },
  {
    "shape_pt_sequence" : 96,
    "shape_id" : "1B223DB9-78C8-4A42-8F3E-62EC9CB60AA7",
    "shape_pt_lon" : 28.267765999999995,
    "shape_pt_lat" : 41.240907999999997
  },
  {
    "shape_pt_sequence" : 97,
    "shape_id" : "1B223DB9-78C8-4A42-8F3E-62EC9CB60AA7",
    "shape_pt_lon" : 28.255133000000029,
    "shape_pt_lat" : 41.24053
  },
  {
    "shape_pt_sequence" : 98,
    "shape_id" : "1B223DB9-78C8-4A42-8F3E-62EC9CB60AA7",
    "shape_pt_lon" : 28.242038000000036,
    "shape_pt_lat" : 41.245484999999995
  },
  {
    "shape_pt_sequence" : 99,
    "shape_id" : "1B223DB9-78C8-4A42-8F3E-62EC9CB60AA7",
    "shape_pt_lon" : 28.222470999999985,
    "shape_pt_lat" : 41.243857999999996
  },
  {
    "shape_pt_sequence" : 100,
    "shape_id" : "1B223DB9-78C8-4A42-8F3E-62EC9CB60AA7",
    "shape_pt_lon" : 28.211235999999985,
    "shape_pt_lat" : 41.237814999999983
  },
  {
    "shape_pt_sequence" : 101,
    "shape_id" : "1B223DB9-78C8-4A42-8F3E-62EC9CB60AA7",
    "shape_pt_lon" : 28.200471999999991,
    "shape_pt_lat" : 41.235268999999988
  },
  {
    "shape_pt_sequence" : 102,
    "shape_id" : "1B223DB9-78C8-4A42-8F3E-62EC9CB60AA7",
    "shape_pt_lon" : 28.186646000000025,
    "shape_pt_lat" : 41.228646999999995
  },
  {
    "shape_pt_sequence" : 103,
    "shape_id" : "1B223DB9-78C8-4A42-8F3E-62EC9CB60AA7",
    "shape_pt_lon" : 28.169850999999994,
    "shape_pt_lat" : 41.232320999999999
  },
  {
    "shape_pt_sequence" : 104,
    "shape_id" : "1B223DB9-78C8-4A42-8F3E-62EC9CB60AA7",
    "shape_pt_lon" : 28.163508000000007,
    "shape_pt_lat" : 41.23296599999999
  },
  {
    "shape_pt_sequence" : 105,
    "shape_id" : "1B223DB9-78C8-4A42-8F3E-62EC9CB60AA7",
    "shape_pt_lon" : 28.15020100000001,
    "shape_pt_lat" : 41.245207999999998
  },
  {
    "shape_pt_sequence" : 106,
    "shape_id" : "1B223DB9-78C8-4A42-8F3E-62EC9CB60AA7",
    "shape_pt_lon" : 28.13904100000002,
    "shape_pt_lat" : 41.258547999999998
  },
  {
    "shape_pt_sequence" : 107,
    "shape_id" : "1B223DB9-78C8-4A42-8F3E-62EC9CB60AA7",
    "shape_pt_lon" : 28.117390999999998,
    "shape_pt_lat" : 41.260115999999989
  },
  {
    "shape_pt_sequence" : 108,
    "shape_id" : "1B223DB9-78C8-4A42-8F3E-62EC9CB60AA7",
    "shape_pt_lon" : 28.096306000000027,
    "shape_pt_lat" : 41.262028000000001
  },
  {
    "shape_pt_sequence" : 109,
    "shape_id" : "1B223DB9-78C8-4A42-8F3E-62EC9CB60AA7",
    "shape_pt_lon" : 28.084693000000044,
    "shape_pt_lat" : 41.263022999999983
  },
  {
    "shape_pt_sequence" : 110,
    "shape_id" : "1B223DB9-78C8-4A42-8F3E-62EC9CB60AA7",
    "shape_pt_lon" : 28.076740999999998,
    "shape_pt_lat" : 41.265387999999994
  },
  {
    "shape_pt_sequence" : 111,
    "shape_id" : "1B223DB9-78C8-4A42-8F3E-62EC9CB60AA7",
    "shape_pt_lon" : 28.072164999999984,
    "shape_pt_lat" : 41.271711000000003
  },
  {
    "shape_pt_sequence" : 112,
    "shape_id" : "1B223DB9-78C8-4A42-8F3E-62EC9CB60AA7",
    "shape_pt_lon" : 28.065956,
    "shape_pt_lat" : 41.275977999999995
  },
  {
    "shape_pt_sequence" : 113,
    "shape_id" : "1B223DB9-78C8-4A42-8F3E-62EC9CB60AA7",
    "shape_pt_lon" : 28.053356000000036,
    "shape_pt_lat" : 41.280297999999995
  },
  {
    "shape_pt_sequence" : 114,
    "shape_id" : "1B223DB9-78C8-4A42-8F3E-62EC9CB60AA7",
    "shape_pt_lon" : 28.045412000000027,
    "shape_pt_lat" : 41.281590000000001
  },
  {
    "shape_pt_sequence" : 115,
    "shape_id" : "1B223DB9-78C8-4A42-8F3E-62EC9CB60AA7",
    "shape_pt_lon" : 28.027202000000017,
    "shape_pt_lat" : 41.277034999999991
  },
  {
    "shape_pt_sequence" : 116,
    "shape_id" : "1B223DB9-78C8-4A42-8F3E-62EC9CB60AA7",
    "shape_pt_lon" : 28.019134000000037,
    "shape_pt_lat" : 41.278877999999992
  },
  {
    "shape_pt_sequence" : 117,
    "shape_id" : "1B223DB9-78C8-4A42-8F3E-62EC9CB60AA7",
    "shape_pt_lon" : 28.010617999999994,
    "shape_pt_lat" : 41.279395999999984
  },
  {
    "shape_pt_sequence" : 118,
    "shape_id" : "1B223DB9-78C8-4A42-8F3E-62EC9CB60AA7",
    "shape_pt_lon" : 28.010617999999994,
    "shape_pt_lat" : 41.279395999999984
  },
  {
    "shape_pt_sequence" : 119,
    "shape_id" : "1B223DB9-78C8-4A42-8F3E-62EC9CB60AA7",
    "shape_pt_lon" : 28.010617999999994,
    "shape_pt_lat" : 41.279395999999984
  },
  {
    "shape_pt_sequence" : 120,
    "shape_id" : "1B223DB9-78C8-4A42-8F3E-62EC9CB60AA7",
    "shape_pt_lon" : 27.999690999999984,
    "shape_pt_lat" : 41.279344000000009
  },
  {
    "shape_pt_sequence" : 121,
    "shape_id" : "1B223DB9-78C8-4A42-8F3E-62EC9CB60AA7",
    "shape_pt_lon" : 27.991378999999995,
    "shape_pt_lat" : 41.276854999999998
  },
  {
    "shape_pt_sequence" : 122,
    "shape_id" : "1B223DB9-78C8-4A42-8F3E-62EC9CB60AA7",
    "shape_pt_lon" : 27.983700000000027,
    "shape_pt_lat" : 41.27785200000001
  },
  {
    "shape_pt_sequence" : 123,
    "shape_id" : "1B223DB9-78C8-4A42-8F3E-62EC9CB60AA7",
    "shape_pt_lon" : 27.975204999999988,
    "shape_pt_lat" : 41.274877999999994
  },
  {
    "shape_pt_sequence" : 124,
    "shape_id" : "1B223DB9-78C8-4A42-8F3E-62EC9CB60AA7",
    "shape_pt_lon" : 27.962044999999989,
    "shape_pt_lat" : 41.272607999999991
  },
  {
    "shape_pt_sequence" : 125,
    "shape_id" : "1B223DB9-78C8-4A42-8F3E-62EC9CB60AA7",
    "shape_pt_lon" : 27.953939999999989,
    "shape_pt_lat" : 41.268860000000011
  },
  {
    "shape_pt_sequence" : 126,
    "shape_id" : "1B223DB9-78C8-4A42-8F3E-62EC9CB60AA7",
    "shape_pt_lon" : 27.939977999999996,
    "shape_pt_lat" : 41.268260000000005
  },
  {
    "shape_pt_sequence" : 127,
    "shape_id" : "1B223DB9-78C8-4A42-8F3E-62EC9CB60AA7",
    "shape_pt_lon" : 27.929364000000021,
    "shape_pt_lat" : 41.261035999999997
  },
  {
    "shape_pt_sequence" : 128,
    "shape_id" : "1B223DB9-78C8-4A42-8F3E-62EC9CB60AA7",
    "shape_pt_lon" : 27.922911000000028,
    "shape_pt_lat" : 41.259039999999992
  },
  {
    "shape_pt_sequence" : 129,
    "shape_id" : "1B223DB9-78C8-4A42-8F3E-62EC9CB60AA7",
    "shape_pt_lon" : 27.91312099999999,
    "shape_pt_lat" : 41.256069999999994
  },
  {
    "shape_pt_sequence" : 130,
    "shape_id" : "1B223DB9-78C8-4A42-8F3E-62EC9CB60AA7",
    "shape_pt_lon" : 27.904363000000018,
    "shape_pt_lat" : 41.259773999999986
  },
  {
    "shape_pt_sequence" : 131,
    "shape_id" : "1B223DB9-78C8-4A42-8F3E-62EC9CB60AA7",
    "shape_pt_lon" : 27.898935999999992,
    "shape_pt_lat" : 41.257700999999997
  },
  {
    "shape_pt_sequence" : 132,
    "shape_id" : "1B223DB9-78C8-4A42-8F3E-62EC9CB60AA7",
    "shape_pt_lon" : 27.88570900000002,
    "shape_pt_lat" : 41.246630000000003
  },
  {
    "shape_pt_sequence" : 133,
    "shape_id" : "1B223DB9-78C8-4A42-8F3E-62EC9CB60AA7",
    "shape_pt_lon" : 27.879705999999999,
    "shape_pt_lat" : 41.241799999999998
  },
  {
    "shape_pt_sequence" : 134,
    "shape_id" : "1B223DB9-78C8-4A42-8F3E-62EC9CB60AA7",
    "shape_pt_lon" : 27.873563000000019,
    "shape_pt_lat" : 41.238840000000003
  },
  {
    "shape_pt_sequence" : 135,
    "shape_id" : "1B223DB9-78C8-4A42-8F3E-62EC9CB60AA7",
    "shape_pt_lon" : 27.864485000000002,
    "shape_pt_lat" : 41.231820999999997
  },
  {
    "shape_pt_sequence" : 136,
    "shape_id" : "1B223DB9-78C8-4A42-8F3E-62EC9CB60AA7",
    "shape_pt_lon" : 27.852445000000017,
    "shape_pt_lat" : 41.222377999999985
  },
  {
    "shape_pt_sequence" : 137,
    "shape_id" : "1B223DB9-78C8-4A42-8F3E-62EC9CB60AA7",
    "shape_pt_lon" : 27.845958000000024,
    "shape_pt_lat" : 41.220252999999992
  },
  {
    "shape_pt_sequence" : 138,
    "shape_id" : "1B223DB9-78C8-4A42-8F3E-62EC9CB60AA7",
    "shape_pt_lon" : 27.838410000000039,
    "shape_pt_lat" : 41.210651000000013
  },
  {
    "shape_pt_sequence" : 139,
    "shape_id" : "1B223DB9-78C8-4A42-8F3E-62EC9CB60AA7",
    "shape_pt_lon" : 27.828866000000033,
    "shape_pt_lat" : 41.206300999999989
  },
  {
    "shape_pt_sequence" : 140,
    "shape_id" : "1B223DB9-78C8-4A42-8F3E-62EC9CB60AA7",
    "shape_pt_lon" : 27.825733000000014,
    "shape_pt_lat" : 41.202274999999993
  },
  {
    "shape_pt_sequence" : 141,
    "shape_id" : "1B223DB9-78C8-4A42-8F3E-62EC9CB60AA7",
    "shape_pt_lon" : 27.820196000000038,
    "shape_pt_lat" : 41.20042500000001
  },
  {
    "shape_pt_sequence" : 142,
    "shape_id" : "1B223DB9-78C8-4A42-8F3E-62EC9CB60AA7",
    "shape_pt_lon" : 27.817385999999971,
    "shape_pt_lat" : 41.196597999999994
  },
  {
    "shape_pt_sequence" : 143,
    "shape_id" : "1B223DB9-78C8-4A42-8F3E-62EC9CB60AA7",
    "shape_pt_lon" : 27.811960000000028,
    "shape_pt_lat" : 41.193390000000001
  },
  {
    "shape_pt_sequence" : 144,
    "shape_id" : "1B223DB9-78C8-4A42-8F3E-62EC9CB60AA7",
    "shape_pt_lon" : 27.805856000000034,
    "shape_pt_lat" : 41.188520999999994
  },
  {
    "shape_pt_sequence" : 145,
    "shape_id" : "1B223DB9-78C8-4A42-8F3E-62EC9CB60AA7",
    "shape_pt_lon" : 27.784347999999994,
    "shape_pt_lat" : 41.177828000000005
  },
  {
    "shape_pt_sequence" : 146,
    "shape_id" : "1B223DB9-78C8-4A42-8F3E-62EC9CB60AA7",
    "shape_pt_lon" : 27.776571999999987,
    "shape_pt_lat" : 41.177999999999997
  },
  {
    "shape_pt_sequence" : 147,
    "shape_id" : "1B223DB9-78C8-4A42-8F3E-62EC9CB60AA7",
    "shape_pt_lon" : 27.771403000000021,
    "shape_pt_lat" : 41.17643799999999
  },
  {
    "shape_pt_sequence" : 148,
    "shape_id" : "1B223DB9-78C8-4A42-8F3E-62EC9CB60AA7",
    "shape_pt_lon" : 27.74408600000001,
    "shape_pt_lat" : 41.169425999999994
  },
  {
    "shape_pt_sequence" : 149,
    "shape_id" : "1B223DB9-78C8-4A42-8F3E-62EC9CB60AA7",
    "shape_pt_lon" : 27.729318000000006,
    "shape_pt_lat" : 41.168894999999992
  },
  {
    "shape_pt_sequence" : 150,
    "shape_id" : "1B223DB9-78C8-4A42-8F3E-62EC9CB60AA7",
    "shape_pt_lon" : 27.703404000000006,
    "shape_pt_lat" : 41.161881000000008
  },
  {
    "shape_pt_sequence" : 151,
    "shape_id" : "1B223DB9-78C8-4A42-8F3E-62EC9CB60AA7",
    "shape_pt_lon" : 27.67548800000003,
    "shape_pt_lat" : 41.150925000000001
  },
  {
    "shape_pt_sequence" : 152,
    "shape_id" : "1B223DB9-78C8-4A42-8F3E-62EC9CB60AA7",
    "shape_pt_lon" : 27.66431,
    "shape_pt_lat" : 41.150466000000002
  },
  {
    "shape_pt_sequence" : 153,
    "shape_id" : "1B223DB9-78C8-4A42-8F3E-62EC9CB60AA7",
    "shape_pt_lon" : 27.654355000000038,
    "shape_pt_lat" : 41.144975999999993
  },
  {
    "shape_pt_sequence" : 154,
    "shape_id" : "1B223DB9-78C8-4A42-8F3E-62EC9CB60AA7",
    "shape_pt_lon" : 27.644113000000004,
    "shape_pt_lat" : 41.142754999999987
  },
  {
    "shape_pt_sequence" : 155,
    "shape_id" : "1B223DB9-78C8-4A42-8F3E-62EC9CB60AA7",
    "shape_pt_lon" : 27.636778000000021,
    "shape_pt_lat" : 41.142167999999998
  },
  {
    "shape_pt_sequence" : 156,
    "shape_id" : "1B223DB9-78C8-4A42-8F3E-62EC9CB60AA7",
    "shape_pt_lon" : 27.630603000000008,
    "shape_pt_lat" : 41.141143
  },
  {
    "shape_pt_sequence" : 157,
    "shape_id" : "1B223DB9-78C8-4A42-8F3E-62EC9CB60AA7",
    "shape_pt_lon" : 27.624157999999994,
    "shape_pt_lat" : 41.138894999999984
  },
  {
    "shape_pt_sequence" : 158,
    "shape_id" : "1B223DB9-78C8-4A42-8F3E-62EC9CB60AA7",
    "shape_pt_lon" : 27.602032000000008,
    "shape_pt_lat" : 41.140313999999996
  },
  {
    "shape_pt_sequence" : 159,
    "shape_id" : "1B223DB9-78C8-4A42-8F3E-62EC9CB60AA7",
    "shape_pt_lon" : 27.588321000000008,
    "shape_pt_lat" : 41.14153499999999
  },
  {
    "shape_pt_sequence" : 160,
    "shape_id" : "1B223DB9-78C8-4A42-8F3E-62EC9CB60AA7",
    "shape_pt_lon" : 27.579295000000002,
    "shape_pt_lat" : 41.14129599999999
  },
  {
    "shape_pt_sequence" : 161,
    "shape_id" : "1B223DB9-78C8-4A42-8F3E-62EC9CB60AA7",
    "shape_pt_lon" : 27.575913000000043,
    "shape_pt_lat" : 41.145573000000006
  },
  {
    "shape_pt_sequence" : 162,
    "shape_id" : "1B223DB9-78C8-4A42-8F3E-62EC9CB60AA7",
    "shape_pt_lon" : 27.572545000000019,
    "shape_pt_lat" : 41.147740999999996
  },
  {
    "shape_pt_sequence" : 163,
    "shape_id" : "1B223DB9-78C8-4A42-8F3E-62EC9CB60AA7",
    "shape_pt_lon" : 27.552510000000041,
    "shape_pt_lat" : 41.144606000000003
  },
  {
    "shape_pt_sequence" : 164,
    "shape_id" : "1B223DB9-78C8-4A42-8F3E-62EC9CB60AA7",
    "shape_pt_lon" : 27.543035000000003,
    "shape_pt_lat" : 41.146899999999995
  },
  {
    "shape_pt_sequence" : 165,
    "shape_id" : "1B223DB9-78C8-4A42-8F3E-62EC9CB60AA7",
    "shape_pt_lon" : 27.521768000000037,
    "shape_pt_lat" : 41.160991000000003
  },
  {
    "shape_pt_sequence" : 166,
    "shape_id" : "1B223DB9-78C8-4A42-8F3E-62EC9CB60AA7",
    "shape_pt_lon" : 27.505979999999994,
    "shape_pt_lat" : 41.165743999999997
  },
  {
    "shape_pt_sequence" : 167,
    "shape_id" : "1B223DB9-78C8-4A42-8F3E-62EC9CB60AA7",
    "shape_pt_lon" : 27.483392000000009,
    "shape_pt_lat" : 41.182201000000006
  },
  {
    "shape_pt_sequence" : 168,
    "shape_id" : "1B223DB9-78C8-4A42-8F3E-62EC9CB60AA7",
    "shape_pt_lon" : 27.476480000000009,
    "shape_pt_lat" : 41.192163000000001
  },
  {
    "shape_pt_sequence" : 169,
    "shape_id" : "1B223DB9-78C8-4A42-8F3E-62EC9CB60AA7",
    "shape_pt_lon" : 27.478078000000011,
    "shape_pt_lat" : 41.201310999999997
  },
  {
    "shape_pt_sequence" : 170,
    "shape_id" : "1B223DB9-78C8-4A42-8F3E-62EC9CB60AA7",
    "shape_pt_lon" : 27.496690000000001,
    "shape_pt_lat" : 41.218108999999984
  },
  {
    "shape_pt_sequence" : 171,
    "shape_id" : "1B223DB9-78C8-4A42-8F3E-62EC9CB60AA7",
    "shape_pt_lon" : 27.506390000000039,
    "shape_pt_lat" : 41.231445000000001
  },
  {
    "shape_pt_sequence" : 172,
    "shape_id" : "1B223DB9-78C8-4A42-8F3E-62EC9CB60AA7",
    "shape_pt_lon" : 27.505566000000016,
    "shape_pt_lat" : 41.234830000000002
  },
  {
    "shape_pt_sequence" : 173,
    "shape_id" : "1B223DB9-78C8-4A42-8F3E-62EC9CB60AA7",
    "shape_pt_lon" : 27.49495300000001,
    "shape_pt_lat" : 41.236942999999997
  },
  {
    "shape_pt_sequence" : 174,
    "shape_id" : "1B223DB9-78C8-4A42-8F3E-62EC9CB60AA7",
    "shape_pt_lon" : 27.464455999999984,
    "shape_pt_lat" : 41.246797000000001
  },
  {
    "shape_pt_sequence" : 175,
    "shape_id" : "1B223DB9-78C8-4A42-8F3E-62EC9CB60AA7",
    "shape_pt_lon" : 27.458202999999997,
    "shape_pt_lat" : 41.255051999999985
  },
  {
    "shape_pt_sequence" : 176,
    "shape_id" : "1B223DB9-78C8-4A42-8F3E-62EC9CB60AA7",
    "shape_pt_lon" : 27.461609000000038,
    "shape_pt_lat" : 41.26649299999999
  },
  {
    "shape_pt_sequence" : 177,
    "shape_id" : "1B223DB9-78C8-4A42-8F3E-62EC9CB60AA7",
    "shape_pt_lon" : 27.458276000000041,
    "shape_pt_lat" : 41.270199999999996
  },
  {
    "shape_pt_sequence" : 178,
    "shape_id" : "1B223DB9-78C8-4A42-8F3E-62EC9CB60AA7",
    "shape_pt_lon" : 27.444602000000032,
    "shape_pt_lat" : 41.272773999999998
  },
  {
    "shape_pt_sequence" : 179,
    "shape_id" : "1B223DB9-78C8-4A42-8F3E-62EC9CB60AA7",
    "shape_pt_lon" : 27.429518000000002,
    "shape_pt_lat" : 41.284298000000007
  },
  {
    "shape_pt_sequence" : 180,
    "shape_id" : "1B223DB9-78C8-4A42-8F3E-62EC9CB60AA7",
    "shape_pt_lon" : 27.424881999999997,
    "shape_pt_lat" : 41.290084
  },
  {
    "shape_pt_sequence" : 181,
    "shape_id" : "1B223DB9-78C8-4A42-8F3E-62EC9CB60AA7",
    "shape_pt_lon" : 27.42676800000001,
    "shape_pt_lat" : 41.295380000000002
  },
  {
    "shape_pt_sequence" : 182,
    "shape_id" : "1B223DB9-78C8-4A42-8F3E-62EC9CB60AA7",
    "shape_pt_lon" : 27.434928000000042,
    "shape_pt_lat" : 41.300204999999984
  },
  {
    "shape_pt_sequence" : 183,
    "shape_id" : "1B223DB9-78C8-4A42-8F3E-62EC9CB60AA7",
    "shape_pt_lon" : 27.435486999999995,
    "shape_pt_lat" : 41.303476000000011
  },
  {
    "shape_pt_sequence" : 184,
    "shape_id" : "1B223DB9-78C8-4A42-8F3E-62EC9CB60AA7",
    "shape_pt_lon" : 27.431598000000008,
    "shape_pt_lat" : 41.306252999999984
  },
  {
    "shape_pt_sequence" : 185,
    "shape_id" : "1B223DB9-78C8-4A42-8F3E-62EC9CB60AA7",
    "shape_pt_lon" : 27.403539000000023,
    "shape_pt_lat" : 41.310333999999997
  },
  {
    "shape_pt_sequence" : 186,
    "shape_id" : "1B223DB9-78C8-4A42-8F3E-62EC9CB60AA7",
    "shape_pt_lon" : 27.399259000000001,
    "shape_pt_lat" : 41.314598000000004
  },
  {
    "shape_pt_sequence" : 187,
    "shape_id" : "1B223DB9-78C8-4A42-8F3E-62EC9CB60AA7",
    "shape_pt_lon" : 27.398870999999986,
    "shape_pt_lat" : 41.318345999999998
  },
  {
    "shape_pt_sequence" : 188,
    "shape_id" : "1B223DB9-78C8-4A42-8F3E-62EC9CB60AA7",
    "shape_pt_lon" : 27.406272000000001,
    "shape_pt_lat" : 41.327807999999983
  },
  {
    "shape_pt_sequence" : 189,
    "shape_id" : "1B223DB9-78C8-4A42-8F3E-62EC9CB60AA7",
    "shape_pt_lon" : 27.406280000000038,
    "shape_pt_lat" : 41.332076000000001
  },
  {
    "shape_pt_sequence" : 190,
    "shape_id" : "1B223DB9-78C8-4A42-8F3E-62EC9CB60AA7",
    "shape_pt_lon" : 27.393885000000012,
    "shape_pt_lat" : 41.338003999999991
  },
  {
    "shape_pt_sequence" : 191,
    "shape_id" : "1B223DB9-78C8-4A42-8F3E-62EC9CB60AA7",
    "shape_pt_lon" : 27.355617999999993,
    "shape_pt_lat" : 41.347539999999995
  },
  {
    "shape_pt_sequence" : 192,
    "shape_id" : "1B223DB9-78C8-4A42-8F3E-62EC9CB60AA7",
    "shape_pt_lon" : 27.344654999999989,
    "shape_pt_lat" : 41.35492
  },
  {
    "shape_pt_sequence" : 193,
    "shape_id" : "1B223DB9-78C8-4A42-8F3E-62EC9CB60AA7",
    "shape_pt_lon" : 27.326321000000036,
    "shape_pt_lat" : 41.355189000000003
  },
  {
    "shape_pt_sequence" : 194,
    "shape_id" : "1B223DB9-78C8-4A42-8F3E-62EC9CB60AA7",
    "shape_pt_lon" : 27.302787999999964,
    "shape_pt_lat" : 41.354397999999989
  },
  {
    "shape_pt_sequence" : 195,
    "shape_id" : "1B223DB9-78C8-4A42-8F3E-62EC9CB60AA7",
    "shape_pt_lon" : 27.277035000000012,
    "shape_pt_lat" : 41.363191
  },
  {
    "shape_pt_sequence" : 196,
    "shape_id" : "1B223DB9-78C8-4A42-8F3E-62EC9CB60AA7",
    "shape_pt_lon" : 27.256035999999995,
    "shape_pt_lat" : 41.369845000000012
  },
  {
    "shape_pt_sequence" : 197,
    "shape_id" : "1B223DB9-78C8-4A42-8F3E-62EC9CB60AA7",
    "shape_pt_lon" : 27.245429999999999,
    "shape_pt_lat" : 41.374301999999993
  },
  {
    "shape_pt_sequence" : 198,
    "shape_id" : "1B223DB9-78C8-4A42-8F3E-62EC9CB60AA7",
    "shape_pt_lon" : 27.231313000000029,
    "shape_pt_lat" : 41.371302
  },
  {
    "shape_pt_sequence" : 199,
    "shape_id" : "1B223DB9-78C8-4A42-8F3E-62EC9CB60AA7",
    "shape_pt_lon" : 27.192996999999991,
    "shape_pt_lat" : 41.363742999999985
  },
  {
    "shape_pt_sequence" : 200,
    "shape_id" : "1B223DB9-78C8-4A42-8F3E-62EC9CB60AA7",
    "shape_pt_lon" : 27.170932999999991,
    "shape_pt_lat" : 41.365003999999992
  },
  {
    "shape_pt_sequence" : 201,
    "shape_id" : "1B223DB9-78C8-4A42-8F3E-62EC9CB60AA7",
    "shape_pt_lon" : 27.162803000000025,
    "shape_pt_lat" : 41.363581999999994
  },
  {
    "shape_pt_sequence" : 202,
    "shape_id" : "1B223DB9-78C8-4A42-8F3E-62EC9CB60AA7",
    "shape_pt_lon" : 27.139353,
    "shape_pt_lat" : 41.366494999999979
  },
  {
    "shape_pt_sequence" : 203,
    "shape_id" : "1B223DB9-78C8-4A42-8F3E-62EC9CB60AA7",
    "shape_pt_lon" : 27.129638000000028,
    "shape_pt_lat" : 41.364924999999985
  },
  {
    "shape_pt_sequence" : 204,
    "shape_id" : "1B223DB9-78C8-4A42-8F3E-62EC9CB60AA7",
    "shape_pt_lon" : 27.114294999999998,
    "shape_pt_lat" : 41.367849999999997
  },
  {
    "shape_pt_sequence" : 205,
    "shape_id" : "1B223DB9-78C8-4A42-8F3E-62EC9CB60AA7",
    "shape_pt_lon" : 27.106370999999996,
    "shape_pt_lat" : 41.368151000000005
  },
  {
    "shape_pt_sequence" : 206,
    "shape_id" : "1B223DB9-78C8-4A42-8F3E-62EC9CB60AA7",
    "shape_pt_lon" : 27.081569999999999,
    "shape_pt_lat" : 41.359833999999999
  },
  {
    "shape_pt_sequence" : 207,
    "shape_id" : "1B223DB9-78C8-4A42-8F3E-62EC9CB60AA7",
    "shape_pt_lon" : 27.062280999999984,
    "shape_pt_lat" : 41.349705000000007
  },
  {
    "shape_pt_sequence" : 208,
    "shape_id" : "1B223DB9-78C8-4A42-8F3E-62EC9CB60AA7",
    "shape_pt_lon" : 27.046506999999991,
    "shape_pt_lat" : 41.34840299999999
  },
  {
    "shape_pt_sequence" : 209,
    "shape_id" : "1B223DB9-78C8-4A42-8F3E-62EC9CB60AA7",
    "shape_pt_lon" : 27.031628999999981,
    "shape_pt_lat" : 41.353132000000002
  },
  {
    "shape_pt_sequence" : 210,
    "shape_id" : "1B223DB9-78C8-4A42-8F3E-62EC9CB60AA7",
    "shape_pt_lon" : 27.018913000000026,
    "shape_pt_lat" : 41.360911000000002
  },
  {
    "shape_pt_sequence" : 211,
    "shape_id" : "1B223DB9-78C8-4A42-8F3E-62EC9CB60AA7",
    "shape_pt_lon" : 27.007338000000004,
    "shape_pt_lat" : 41.366077999999995
  },
  {
    "shape_pt_sequence" : 212,
    "shape_id" : "1B223DB9-78C8-4A42-8F3E-62EC9CB60AA7",
    "shape_pt_lon" : 26.989188000000041,
    "shape_pt_lat" : 41.369574999999998
  },
  {
    "shape_pt_sequence" : 213,
    "shape_id" : "1B223DB9-78C8-4A42-8F3E-62EC9CB60AA7",
    "shape_pt_lon" : 26.981337999999994,
    "shape_pt_lat" : 41.365380999999999
  },
  {
    "shape_pt_sequence" : 214,
    "shape_id" : "1B223DB9-78C8-4A42-8F3E-62EC9CB60AA7",
    "shape_pt_lon" : 26.970014999999989,
    "shape_pt_lat" : 41.36018
  },
  {
    "shape_pt_sequence" : 215,
    "shape_id" : "1B223DB9-78C8-4A42-8F3E-62EC9CB60AA7",
    "shape_pt_lon" : 26.953288000000015,
    "shape_pt_lat" : 41.355077999999999
  },
  {
    "shape_pt_sequence" : 216,
    "shape_id" : "1B223DB9-78C8-4A42-8F3E-62EC9CB60AA7",
    "shape_pt_lon" : 26.947528000000005,
    "shape_pt_lat" : 41.3461
  },
  {
    "shape_pt_sequence" : 217,
    "shape_id" : "1B223DB9-78C8-4A42-8F3E-62EC9CB60AA7",
    "shape_pt_lon" : 26.914591999999999,
    "shape_pt_lat" : 41.346259000000003
  },
  {
    "shape_pt_sequence" : 218,
    "shape_id" : "1B223DB9-78C8-4A42-8F3E-62EC9CB60AA7",
    "shape_pt_lon" : 26.892402000000004,
    "shape_pt_lat" : 41.347366999999998
  },
  {
    "shape_pt_sequence" : 219,
    "shape_id" : "1B223DB9-78C8-4A42-8F3E-62EC9CB60AA7",
    "shape_pt_lon" : 26.886675000000025,
    "shape_pt_lat" : 41.350195000000006
  },
  {
    "shape_pt_sequence" : 220,
    "shape_id" : "1B223DB9-78C8-4A42-8F3E-62EC9CB60AA7",
    "shape_pt_lon" : 26.882948999999996,
    "shape_pt_lat" : 41.357385999999991
  },
  {
    "shape_pt_sequence" : 221,
    "shape_id" : "1B223DB9-78C8-4A42-8F3E-62EC9CB60AA7",
    "shape_pt_lon" : 26.876426000000038,
    "shape_pt_lat" : 41.361209999999993
  },
  {
    "shape_pt_sequence" : 222,
    "shape_id" : "1B223DB9-78C8-4A42-8F3E-62EC9CB60AA7",
    "shape_pt_lon" : 26.868863000000033,
    "shape_pt_lat" : 41.365369999999999
  },
  {
    "shape_pt_sequence" : 223,
    "shape_id" : "1B223DB9-78C8-4A42-8F3E-62EC9CB60AA7",
    "shape_pt_lon" : 26.865272000000033,
    "shape_pt_lat" : 41.370973000000014
  },
  {
    "shape_pt_sequence" : 224,
    "shape_id" : "1B223DB9-78C8-4A42-8F3E-62EC9CB60AA7",
    "shape_pt_lon" : 26.856761000000006,
    "shape_pt_lat" : 41.378352999999983
  },
  {
    "shape_pt_sequence" : 225,
    "shape_id" : "1B223DB9-78C8-4A42-8F3E-62EC9CB60AA7",
    "shape_pt_lon" : 26.843689000000012,
    "shape_pt_lat" : 41.38951999999999
  },
  {
    "shape_pt_sequence" : 226,
    "shape_id" : "1B223DB9-78C8-4A42-8F3E-62EC9CB60AA7",
    "shape_pt_lon" : 26.82955400000003,
    "shape_pt_lat" : 41.404493999999993
  },
  {
    "shape_pt_sequence" : 227,
    "shape_id" : "1B223DB9-78C8-4A42-8F3E-62EC9CB60AA7",
    "shape_pt_lon" : 26.80966699999999,
    "shape_pt_lat" : 41.42699600000001
  },
  {
    "shape_pt_sequence" : 228,
    "shape_id" : "1B223DB9-78C8-4A42-8F3E-62EC9CB60AA7",
    "shape_pt_lon" : 26.801284000000038,
    "shape_pt_lat" : 41.434158999999994
  },
  {
    "shape_pt_sequence" : 229,
    "shape_id" : "1B223DB9-78C8-4A42-8F3E-62EC9CB60AA7",
    "shape_pt_lon" : 26.785797000000002,
    "shape_pt_lat" : 41.443032000000002
  },
  {
    "shape_pt_sequence" : 230,
    "shape_id" : "1B223DB9-78C8-4A42-8F3E-62EC9CB60AA7",
    "shape_pt_lon" : 26.757464000000027,
    "shape_pt_lat" : 41.477606000000016
  },
  {
    "shape_pt_sequence" : 231,
    "shape_id" : "1B223DB9-78C8-4A42-8F3E-62EC9CB60AA7",
    "shape_pt_lon" : 26.754160000000013,
    "shape_pt_lat" : 41.488826999999993
  },
  {
    "shape_pt_sequence" : 232,
    "shape_id" : "1B223DB9-78C8-4A42-8F3E-62EC9CB60AA7",
    "shape_pt_lon" : 26.742257999999964,
    "shape_pt_lat" : 41.503991999999982
  },
  {
    "shape_pt_sequence" : 233,
    "shape_id" : "1B223DB9-78C8-4A42-8F3E-62EC9CB60AA7",
    "shape_pt_lon" : 26.740445000000022,
    "shape_pt_lat" : 41.510041000000001
  },
  {
    "shape_pt_sequence" : 234,
    "shape_id" : "1B223DB9-78C8-4A42-8F3E-62EC9CB60AA7",
    "shape_pt_lon" : 26.733883999999989,
    "shape_pt_lat" : 41.51461299999999
  },
  {
    "shape_pt_sequence" : 235,
    "shape_id" : "1B223DB9-78C8-4A42-8F3E-62EC9CB60AA7",
    "shape_pt_lon" : 26.722749999999991,
    "shape_pt_lat" : 41.529044999999996
  },
  {
    "shape_pt_sequence" : 236,
    "shape_id" : "1B223DB9-78C8-4A42-8F3E-62EC9CB60AA7",
    "shape_pt_lon" : 26.702596000000028,
    "shape_pt_lat" : 41.557701000000002
  },
  {
    "shape_pt_sequence" : 237,
    "shape_id" : "1B223DB9-78C8-4A42-8F3E-62EC9CB60AA7",
    "shape_pt_lon" : 26.688119999999998,
    "shape_pt_lat" : 41.572172000000002
  },
  {
    "shape_pt_sequence" : 238,
    "shape_id" : "1B223DB9-78C8-4A42-8F3E-62EC9CB60AA7",
    "shape_pt_lon" : 26.670183000000009,
    "shape_pt_lat" : 41.580147999999994
  },
  {
    "shape_pt_sequence" : 239,
    "shape_id" : "1B223DB9-78C8-4A42-8F3E-62EC9CB60AA7",
    "shape_pt_lon" : 26.658131000000026,
    "shape_pt_lat" : 41.585313999999983
  },
  {
    "shape_pt_sequence" : 240,
    "shape_id" : "1B223DB9-78C8-4A42-8F3E-62EC9CB60AA7",
    "shape_pt_lon" : 26.653314999999992,
    "shape_pt_lat" : 41.599477999999998
  },
  {
    "shape_pt_sequence" : 241,
    "shape_id" : "1B223DB9-78C8-4A42-8F3E-62EC9CB60AA7",
    "shape_pt_lon" : 26.64713500000002,
    "shape_pt_lat" : 41.609045000000009
  },
  {
    "shape_pt_sequence" : 242,
    "shape_id" : "1B223DB9-78C8-4A42-8F3E-62EC9CB60AA7",
    "shape_pt_lon" : 26.605310000000031,
    "shape_pt_lat" : 41.636485999999998
  },
  {
    "shape_pt_sequence" : 243,
    "shape_id" : "1B223DB9-78C8-4A42-8F3E-62EC9CB60AA7",
    "shape_pt_lon" : 26.579948999999999,
    "shape_pt_lat" : 41.655252999999988
  },
  {
    "shape_pt_sequence" : 244,
    "shape_id" : "1B223DB9-78C8-4A42-8F3E-62EC9CB60AA7",
    "shape_pt_lon" : 26.579948999999999,
    "shape_pt_lat" : 41.655252999999988
  },
  {
    "shape_pt_sequence" : 245,
    "shape_id" : "1B223DB9-78C8-4A42-8F3E-62EC9CB60AA7",
    "shape_pt_lon" : 26.579948999999999,
    "shape_pt_lat" : 41.655252999999988
  },
  {
    "shape_pt_sequence" : 246,
    "shape_id" : "1B223DB9-78C8-4A42-8F3E-62EC9CB60AA7",
    "shape_pt_lon" : 26.578250999999995,
    "shape_pt_lat" : 41.656520999999991
  },
  {
    "shape_pt_sequence" : 247,
    "shape_id" : "1B223DB9-78C8-4A42-8F3E-62EC9CB60AA7",
    "shape_pt_lon" : 26.567215000000033,
    "shape_pt_lat" : 41.661433000000009
  },
  {
    "shape_pt_sequence" : 248,
    "shape_id" : "1B223DB9-78C8-4A42-8F3E-62EC9CB60AA7",
    "shape_pt_lon" : 26.554349999999999,
    "shape_pt_lat" : 41.669570999999998
  },
  {
    "shape_pt_sequence" : 249,
    "shape_id" : "1B223DB9-78C8-4A42-8F3E-62EC9CB60AA7",
    "shape_pt_lon" : 26.547985000000011,
    "shape_pt_lat" : 41.670899000000006
  },
  {
    "shape_pt_sequence" : 250,
    "shape_id" : "1B223DB9-78C8-4A42-8F3E-62EC9CB60AA7",
    "shape_pt_lon" : 26.529311000000007,
    "shape_pt_lat" : 41.674537999999998
  },
  {
    "shape_pt_sequence" : 251,
    "shape_id" : "1B223DB9-78C8-4A42-8F3E-62EC9CB60AA7",
    "shape_pt_lon" : 26.496312999999986,
    "shape_pt_lat" : 41.682300999999995
  },
  {
    "shape_pt_sequence" : 252,
    "shape_id" : "1B223DB9-78C8-4A42-8F3E-62EC9CB60AA7",
    "shape_pt_lon" : 26.482730000000032,
    "shape_pt_lat" : 41.68558500000001
  },
  {
    "shape_pt_sequence" : 253,
    "shape_id" : "1B223DB9-78C8-4A42-8F3E-62EC9CB60AA7",
    "shape_pt_lon" : 26.445081000000016,
    "shape_pt_lat" : 41.693505000000009
  },
  {
    "shape_pt_sequence" : 254,
    "shape_id" : "1B223DB9-78C8-4A42-8F3E-62EC9CB60AA7",
    "shape_pt_lon" : 26.428892999999988,
    "shape_pt_lat" : 41.699625000000005
  },
  {
    "shape_pt_sequence" : 255,
    "shape_id" : "1B223DB9-78C8-4A42-8F3E-62EC9CB60AA7",
    "shape_pt_lon" : 26.387428,
    "shape_pt_lat" : 41.710147999999982
  },
  {
    "shape_pt_sequence" : 256,
    "shape_id" : "1B223DB9-78C8-4A42-8F3E-62EC9CB60AA7",
    "shape_pt_lon" : 26.361308000000008,
    "shape_pt_lat" : 41.719177999999992
  },
  {
    "shape_pt_sequence" : 257,
    "shape_id" : "1B223DB9-78C8-4A42-8F3E-62EC9CB60AA7",
    "shape_pt_lon" : 26.361308000000008,
    "shape_pt_lat" : 41.719177999999992
  },
  {
    "shape_pt_sequence" : 258,
    "shape_id" : "1B223DB9-78C8-4A42-8F3E-62EC9CB60AA7",
    "shape_pt_lon" : 26.361298000000001,
    "shape_pt_lat" : 41.719161999999997
  },
  {
    "shape_pt_sequence" : 259,
    "shape_id" : "1B223DB9-78C8-4A42-8F3E-62EC9CB60AA7",
    "shape_pt_lon" : 26.201655735473999,
    "shape_pt_lat" : 41.766607018080997
  },
  {
    "shape_pt_sequence" : 260,
    "shape_id" : "1B223DB9-78C8-4A42-8F3E-62EC9CB60AA7",
    "shape_pt_lon" : 26.201655735473999,
    "shape_pt_lat" : 41.766607018080997
  },
  {
    "shape_pt_sequence" : 261,
    "shape_id" : "1B223DB9-78C8-4A42-8F3E-62EC9CB60AA7",
    "shape_pt_lon" : 25.586314099999999,
    "shape_pt_lat" : 42.057140799999999
  },
  {
    "shape_pt_sequence" : 262,
    "shape_id" : "1B223DB9-78C8-4A42-8F3E-62EC9CB60AA7",
    "shape_pt_lon" : 25.586025999999976,
    "shape_pt_lat" : 42.056373000000008
  },
  {
    "shape_pt_sequence" : 263,
    "shape_id" : "1B223DB9-78C8-4A42-8F3E-62EC9CB60AA7",
    "shape_pt_lon" : 25.581052999999997,
    "shape_pt_lat" : 42.057177000000003
  },
  {
    "shape_pt_sequence" : 264,
    "shape_id" : "1B223DB9-78C8-4A42-8F3E-62EC9CB60AA7",
    "shape_pt_lon" : 25.564763999999997,
    "shape_pt_lat" : 42.054200999999985
  },
  {
    "shape_pt_sequence" : 265,
    "shape_id" : "1B223DB9-78C8-4A42-8F3E-62EC9CB60AA7",
    "shape_pt_lon" : 25.54077300000003,
    "shape_pt_lat" : 42.060662000000001
  },
  {
    "shape_pt_sequence" : 266,
    "shape_id" : "1B223DB9-78C8-4A42-8F3E-62EC9CB60AA7",
    "shape_pt_lon" : 25.514562000000012,
    "shape_pt_lat" : 42.061631999999996
  },
  {
    "shape_pt_sequence" : 267,
    "shape_id" : "1B223DB9-78C8-4A42-8F3E-62EC9CB60AA7",
    "shape_pt_lon" : 25.491629000000017,
    "shape_pt_lat" : 42.064071999999989
  },
  {
    "shape_pt_sequence" : 268,
    "shape_id" : "1B223DB9-78C8-4A42-8F3E-62EC9CB60AA7",
    "shape_pt_lon" : 25.471137999999996,
    "shape_pt_lat" : 42.065497000000001
  },
  {
    "shape_pt_sequence" : 269,
    "shape_id" : "1B223DB9-78C8-4A42-8F3E-62EC9CB60AA7",
    "shape_pt_lon" : 25.454199000000017,
    "shape_pt_lat" : 42.071934999999989
  },
  {
    "shape_pt_sequence" : 270,
    "shape_id" : "1B223DB9-78C8-4A42-8F3E-62EC9CB60AA7",
    "shape_pt_lon" : 25.416355000000038,
    "shape_pt_lat" : 42.090766999999992
  },
  {
    "shape_pt_sequence" : 271,
    "shape_id" : "1B223DB9-78C8-4A42-8F3E-62EC9CB60AA7",
    "shape_pt_lon" : 25.396441000000038,
    "shape_pt_lat" : 42.096142000000007
  },
  {
    "shape_pt_sequence" : 272,
    "shape_id" : "1B223DB9-78C8-4A42-8F3E-62EC9CB60AA7",
    "shape_pt_lon" : 25.364013,
    "shape_pt_lat" : 42.097277000000005
  },
  {
    "shape_pt_sequence" : 273,
    "shape_id" : "1B223DB9-78C8-4A42-8F3E-62EC9CB60AA7",
    "shape_pt_lon" : 25.342420000000004,
    "shape_pt_lat" : 42.099769000000009
  },
  {
    "shape_pt_sequence" : 274,
    "shape_id" : "1B223DB9-78C8-4A42-8F3E-62EC9CB60AA7",
    "shape_pt_lon" : 25.326405000000022,
    "shape_pt_lat" : 42.102148999999997
  },
  {
    "shape_pt_sequence" : 275,
    "shape_id" : "1B223DB9-78C8-4A42-8F3E-62EC9CB60AA7",
    "shape_pt_lon" : 25.263565000000028,
    "shape_pt_lat" : 42.105092999999997
  },
  {
    "shape_pt_sequence" : 276,
    "shape_id" : "1B223DB9-78C8-4A42-8F3E-62EC9CB60AA7",
    "shape_pt_lon" : 25.231166000000002,
    "shape_pt_lat" : 42.101381000000003
  },
  {
    "shape_pt_sequence" : 277,
    "shape_id" : "1B223DB9-78C8-4A42-8F3E-62EC9CB60AA7",
    "shape_pt_lon" : 25.193902000000037,
    "shape_pt_lat" : 42.097704999999998
  },
  {
    "shape_pt_sequence" : 278,
    "shape_id" : "1B223DB9-78C8-4A42-8F3E-62EC9CB60AA7",
    "shape_pt_lon" : 25.175686000000013,
    "shape_pt_lat" : 42.103940000000001
  },
  {
    "shape_pt_sequence" : 279,
    "shape_id" : "1B223DB9-78C8-4A42-8F3E-62EC9CB60AA7",
    "shape_pt_lon" : 25.147597999999988,
    "shape_pt_lat" : 42.12375200000001
  },
  {
    "shape_pt_sequence" : 280,
    "shape_id" : "1B223DB9-78C8-4A42-8F3E-62EC9CB60AA7",
    "shape_pt_lon" : 25.080996000000027,
    "shape_pt_lat" : 42.134818999999993
  },
  {
    "shape_pt_sequence" : 281,
    "shape_id" : "1B223DB9-78C8-4A42-8F3E-62EC9CB60AA7",
    "shape_pt_lon" : 25.046279999999996,
    "shape_pt_lat" : 42.141441999999998
  },
  {
    "shape_pt_sequence" : 282,
    "shape_id" : "1B223DB9-78C8-4A42-8F3E-62EC9CB60AA7",
    "shape_pt_lon" : 25.028572000000025,
    "shape_pt_lat" : 42.138047999999991
  },
  {
    "shape_pt_sequence" : 283,
    "shape_id" : "1B223DB9-78C8-4A42-8F3E-62EC9CB60AA7",
    "shape_pt_lon" : 25.006076000000007,
    "shape_pt_lat" : 42.132042000000006
  },
  {
    "shape_pt_sequence" : 284,
    "shape_id" : "1B223DB9-78C8-4A42-8F3E-62EC9CB60AA7",
    "shape_pt_lon" : 24.938049000000035,
    "shape_pt_lat" : 42.131040999999989
  },
  {
    "shape_pt_sequence" : 285,
    "shape_id" : "1B223DB9-78C8-4A42-8F3E-62EC9CB60AA7",
    "shape_pt_lon" : 24.923497999999995,
    "shape_pt_lat" : 42.126452
  },
  {
    "shape_pt_sequence" : 286,
    "shape_id" : "1B223DB9-78C8-4A42-8F3E-62EC9CB60AA7",
    "shape_pt_lon" : 24.891042999999996,
    "shape_pt_lat" : 42.102710999999992
  },
  {
    "shape_pt_sequence" : 287,
    "shape_id" : "1B223DB9-78C8-4A42-8F3E-62EC9CB60AA7",
    "shape_pt_lon" : 24.869382000000002,
    "shape_pt_lat" : 42.101694999999978
  },
  {
    "shape_pt_sequence" : 288,
    "shape_id" : "1B223DB9-78C8-4A42-8F3E-62EC9CB60AA7",
    "shape_pt_lon" : 24.828111000000007,
    "shape_pt_lat" : 42.094766
  },
  {
    "shape_pt_sequence" : 289,
    "shape_id" : "1B223DB9-78C8-4A42-8F3E-62EC9CB60AA7",
    "shape_pt_lon" : 24.814318000000014,
    "shape_pt_lat" : 42.093591000000004
  },
  {
    "shape_pt_sequence" : 290,
    "shape_id" : "1B223DB9-78C8-4A42-8F3E-62EC9CB60AA7",
    "shape_pt_lon" : 24.781447000000014,
    "shape_pt_lat" : 42.113492000000015
  },
  {
    "shape_pt_sequence" : 291,
    "shape_id" : "1B223DB9-78C8-4A42-8F3E-62EC9CB60AA7",
    "shape_pt_lon" : 24.767108000000007,
    "shape_pt_lat" : 42.123367999999985
  },
  {
    "shape_pt_sequence" : 292,
    "shape_id" : "1B223DB9-78C8-4A42-8F3E-62EC9CB60AA7",
    "shape_pt_lon" : 24.760826000000009,
    "shape_pt_lat" : 42.128847999999998
  },
  {
    "shape_pt_sequence" : 293,
    "shape_id" : "1B223DB9-78C8-4A42-8F3E-62EC9CB60AA7",
    "shape_pt_lon" : 24.750603000000012,
    "shape_pt_lat" : 42.134672999999999
  },
  {
    "shape_pt_sequence" : 294,
    "shape_id" : "1B223DB9-78C8-4A42-8F3E-62EC9CB60AA7",
    "shape_pt_lon" : 24.741566000000034,
    "shape_pt_lat" : 42.134325999999994
  },
  {
    "shape_pt_sequence" : 295,
    "shape_id" : "1B223DB9-78C8-4A42-8F3E-62EC9CB60AA7",
    "shape_pt_lon" : 24.741566000000034,
    "shape_pt_lat" : 42.134325999999994
  },
  {
    "shape_pt_sequence" : 296,
    "shape_id" : "1B223DB9-78C8-4A42-8F3E-62EC9CB60AA7",
    "shape_pt_lon" : 24.741565000000037,
    "shape_pt_lat" : 42.134325999999994
  },
  {
    "shape_pt_sequence" : 297,
    "shape_id" : "1B223DB9-78C8-4A42-8F3E-62EC9CB60AA7",
    "shape_pt_lon" : 24.730430000000041,
    "shape_pt_lat" : 42.132246999999985
  },
  {
    "shape_pt_sequence" : 298,
    "shape_id" : "1B223DB9-78C8-4A42-8F3E-62EC9CB60AA7",
    "shape_pt_lon" : 24.683540999999991,
    "shape_pt_lat" : 42.125292999999992
  },
  {
    "shape_pt_sequence" : 299,
    "shape_id" : "1B223DB9-78C8-4A42-8F3E-62EC9CB60AA7",
    "shape_pt_lon" : 24.59940499999999,
    "shape_pt_lat" : 42.13220900000001
  },
  {
    "shape_pt_sequence" : 300,
    "shape_id" : "1B223DB9-78C8-4A42-8F3E-62EC9CB60AA7",
    "shape_pt_lon" : 24.538007000000022,
    "shape_pt_lat" : 42.133331999999996
  },
  {
    "shape_pt_sequence" : 301,
    "shape_id" : "1B223DB9-78C8-4A42-8F3E-62EC9CB60AA7",
    "shape_pt_lon" : 24.506939999999986,
    "shape_pt_lat" : 42.132137
  },
  {
    "shape_pt_sequence" : 302,
    "shape_id" : "1B223DB9-78C8-4A42-8F3E-62EC9CB60AA7",
    "shape_pt_lon" : 24.491919999999993,
    "shape_pt_lat" : 42.133477999999997
  },
  {
    "shape_pt_sequence" : 303,
    "shape_id" : "1B223DB9-78C8-4A42-8F3E-62EC9CB60AA7",
    "shape_pt_lon" : 24.476821000000029,
    "shape_pt_lat" : 42.128956999999993
  },
  {
    "shape_pt_sequence" : 304,
    "shape_id" : "1B223DB9-78C8-4A42-8F3E-62EC9CB60AA7",
    "shape_pt_lon" : 24.468124000000017,
    "shape_pt_lat" : 42.128665000000012
  },
  {
    "shape_pt_sequence" : 305,
    "shape_id" : "1B223DB9-78C8-4A42-8F3E-62EC9CB60AA7",
    "shape_pt_lon" : 24.447104000000024,
    "shape_pt_lat" : 42.13368599999999
  },
  {
    "shape_pt_sequence" : 306,
    "shape_id" : "1B223DB9-78C8-4A42-8F3E-62EC9CB60AA7",
    "shape_pt_lon" : 24.426251000000008,
    "shape_pt_lat" : 42.136015
  },
  {
    "shape_pt_sequence" : 307,
    "shape_id" : "1B223DB9-78C8-4A42-8F3E-62EC9CB60AA7",
    "shape_pt_lon" : 24.405213000000003,
    "shape_pt_lat" : 42.141456999999996
  },
  {
    "shape_pt_sequence" : 308,
    "shape_id" : "1B223DB9-78C8-4A42-8F3E-62EC9CB60AA7",
    "shape_pt_lon" : 24.391521000000012,
    "shape_pt_lat" : 42.140701
  },
  {
    "shape_pt_sequence" : 309,
    "shape_id" : "1B223DB9-78C8-4A42-8F3E-62EC9CB60AA7",
    "shape_pt_lon" : 24.374110000000002,
    "shape_pt_lat" : 42.142290000000003
  },
  {
    "shape_pt_sequence" : 310,
    "shape_id" : "1B223DB9-78C8-4A42-8F3E-62EC9CB60AA7",
    "shape_pt_lon" : 24.354737000000029,
    "shape_pt_lat" : 42.154093999999994
  },
  {
    "shape_pt_sequence" : 311,
    "shape_id" : "1B223DB9-78C8-4A42-8F3E-62EC9CB60AA7",
    "shape_pt_lon" : 24.344640999999996,
    "shape_pt_lat" : 42.159941999999987
  },
  {
    "shape_pt_sequence" : 312,
    "shape_id" : "1B223DB9-78C8-4A42-8F3E-62EC9CB60AA7",
    "shape_pt_lon" : 24.320736000000039,
    "shape_pt_lat" : 42.169757999999995
  },
  {
    "shape_pt_sequence" : 313,
    "shape_id" : "1B223DB9-78C8-4A42-8F3E-62EC9CB60AA7",
    "shape_pt_lon" : 24.320736000000039,
    "shape_pt_lat" : 42.169757999999995
  },
  {
    "shape_pt_sequence" : 314,
    "shape_id" : "1B223DB9-78C8-4A42-8F3E-62EC9CB60AA7",
    "shape_pt_lon" : 24.320736000000039,
    "shape_pt_lat" : 42.169757999999995
  },
  {
    "shape_pt_sequence" : 315,
    "shape_id" : "1B223DB9-78C8-4A42-8F3E-62EC9CB60AA7",
    "shape_pt_lon" : 24.311497000000031,
    "shape_pt_lat" : 42.173544000000007
  },
  {
    "shape_pt_sequence" : 316,
    "shape_id" : "1B223DB9-78C8-4A42-8F3E-62EC9CB60AA7",
    "shape_pt_lon" : 24.292362999999995,
    "shape_pt_lat" : 42.18050800000001
  },
  {
    "shape_pt_sequence" : 317,
    "shape_id" : "1B223DB9-78C8-4A42-8F3E-62EC9CB60AA7",
    "shape_pt_lon" : 24.252289999999988,
    "shape_pt_lat" : 42.185112000000004
  },
  {
    "shape_pt_sequence" : 318,
    "shape_id" : "1B223DB9-78C8-4A42-8F3E-62EC9CB60AA7",
    "shape_pt_lon" : 24.231648000000007,
    "shape_pt_lat" : 42.189318000000007
  },
  {
    "shape_pt_sequence" : 319,
    "shape_id" : "1B223DB9-78C8-4A42-8F3E-62EC9CB60AA7",
    "shape_pt_lon" : 24.196741000000003,
    "shape_pt_lat" : 42.197652000000005
  },
  {
    "shape_pt_sequence" : 320,
    "shape_id" : "1B223DB9-78C8-4A42-8F3E-62EC9CB60AA7",
    "shape_pt_lon" : 24.15249799999998,
    "shape_pt_lat" : 42.202142000000002
  },
  {
    "shape_pt_sequence" : 321,
    "shape_id" : "1B223DB9-78C8-4A42-8F3E-62EC9CB60AA7",
    "shape_pt_lon" : 24.13220400000003,
    "shape_pt_lat" : 42.20429399999999
  },
  {
    "shape_pt_sequence" : 322,
    "shape_id" : "1B223DB9-78C8-4A42-8F3E-62EC9CB60AA7",
    "shape_pt_lon" : 24.13220400000003,
    "shape_pt_lat" : 42.20429399999999
  },
  {
    "shape_pt_sequence" : 323,
    "shape_id" : "1B223DB9-78C8-4A42-8F3E-62EC9CB60AA7",
    "shape_pt_lon" : 24.13220400000003,
    "shape_pt_lat" : 42.20429399999999
  },
  {
    "shape_pt_sequence" : 324,
    "shape_id" : "1B223DB9-78C8-4A42-8F3E-62EC9CB60AA7",
    "shape_pt_lon" : 24.119142000000011,
    "shape_pt_lat" : 42.20547599999999
  },
  {
    "shape_pt_sequence" : 325,
    "shape_id" : "1B223DB9-78C8-4A42-8F3E-62EC9CB60AA7",
    "shape_pt_lon" : 24.033341000000007,
    "shape_pt_lat" : 42.210549999999998
  },
  {
    "shape_pt_sequence" : 326,
    "shape_id" : "1B223DB9-78C8-4A42-8F3E-62EC9CB60AA7",
    "shape_pt_lon" : 24.021353000000005,
    "shape_pt_lat" : 42.215091000000001
  },
  {
    "shape_pt_sequence" : 327,
    "shape_id" : "1B223DB9-78C8-4A42-8F3E-62EC9CB60AA7",
    "shape_pt_lon" : 23.992237000000017,
    "shape_pt_lat" : 42.223839999999996
  },
  {
    "shape_pt_sequence" : 328,
    "shape_id" : "1B223DB9-78C8-4A42-8F3E-62EC9CB60AA7",
    "shape_pt_lon" : 23.963245000000029,
    "shape_pt_lat" : 42.230583999999993
  },
  {
    "shape_pt_sequence" : 329,
    "shape_id" : "1B223DB9-78C8-4A42-8F3E-62EC9CB60AA7",
    "shape_pt_lon" : 23.94581500000001,
    "shape_pt_lat" : 42.241386000000006
  },
  {
    "shape_pt_sequence" : 330,
    "shape_id" : "1B223DB9-78C8-4A42-8F3E-62EC9CB60AA7",
    "shape_pt_lon" : 23.937388999999996,
    "shape_pt_lat" : 42.246344999999984
  },
  {
    "shape_pt_sequence" : 331,
    "shape_id" : "1B223DB9-78C8-4A42-8F3E-62EC9CB60AA7",
    "shape_pt_lon" : 23.927090999999962,
    "shape_pt_lat" : 42.246451999999991
  },
  {
    "shape_pt_sequence" : 332,
    "shape_id" : "1B223DB9-78C8-4A42-8F3E-62EC9CB60AA7",
    "shape_pt_lon" : 23.919477999999998,
    "shape_pt_lat" : 42.248291999999992
  },
  {
    "shape_pt_sequence" : 333,
    "shape_id" : "1B223DB9-78C8-4A42-8F3E-62EC9CB60AA7",
    "shape_pt_lon" : 23.910321000000039,
    "shape_pt_lat" : 42.25588599999999
  },
  {
    "shape_pt_sequence" : 334,
    "shape_id" : "1B223DB9-78C8-4A42-8F3E-62EC9CB60AA7",
    "shape_pt_lon" : 23.906714000000022,
    "shape_pt_lat" : 42.259312999999985
  },
  {
    "shape_pt_sequence" : 335,
    "shape_id" : "1B223DB9-78C8-4A42-8F3E-62EC9CB60AA7",
    "shape_pt_lon" : 23.900690999999995,
    "shape_pt_lat" : 42.260817999999986
  },
  {
    "shape_pt_sequence" : 336,
    "shape_id" : "1B223DB9-78C8-4A42-8F3E-62EC9CB60AA7",
    "shape_pt_lon" : 23.903402,
    "shape_pt_lat" : 42.265552999999976
  },
  {
    "shape_pt_sequence" : 337,
    "shape_id" : "1B223DB9-78C8-4A42-8F3E-62EC9CB60AA7",
    "shape_pt_lon" : 23.899971000000022,
    "shape_pt_lat" : 42.272585000000014
  },
  {
    "shape_pt_sequence" : 338,
    "shape_id" : "1B223DB9-78C8-4A42-8F3E-62EC9CB60AA7",
    "shape_pt_lon" : 23.889752999999985,
    "shape_pt_lat" : 42.282437000000002
  },
  {
    "shape_pt_sequence" : 339,
    "shape_id" : "1B223DB9-78C8-4A42-8F3E-62EC9CB60AA7",
    "shape_pt_lon" : 23.873715000000004,
    "shape_pt_lat" : 42.296214999999989
  },
  {
    "shape_pt_sequence" : 340,
    "shape_id" : "1B223DB9-78C8-4A42-8F3E-62EC9CB60AA7",
    "shape_pt_lon" : 23.862673000000029,
    "shape_pt_lat" : 42.305473999999997
  },
  {
    "shape_pt_sequence" : 341,
    "shape_id" : "1B223DB9-78C8-4A42-8F3E-62EC9CB60AA7",
    "shape_pt_lon" : 23.856605000000002,
    "shape_pt_lat" : 42.313043999999984
  },
  {
    "shape_pt_sequence" : 342,
    "shape_id" : "1B223DB9-78C8-4A42-8F3E-62EC9CB60AA7",
    "shape_pt_lon" : 23.858881000000025,
    "shape_pt_lat" : 42.317975999999994
  },
  {
    "shape_pt_sequence" : 343,
    "shape_id" : "1B223DB9-78C8-4A42-8F3E-62EC9CB60AA7",
    "shape_pt_lon" : 23.868966,
    "shape_pt_lat" : 42.328041000000006
  },
  {
    "shape_pt_sequence" : 344,
    "shape_id" : "1B223DB9-78C8-4A42-8F3E-62EC9CB60AA7",
    "shape_pt_lon" : 23.872126999999978,
    "shape_pt_lat" : 42.333751999999983
  },
  {
    "shape_pt_sequence" : 345,
    "shape_id" : "1B223DB9-78C8-4A42-8F3E-62EC9CB60AA7",
    "shape_pt_lon" : 23.879273000000012,
    "shape_pt_lat" : 42.339120999999984
  },
  {
    "shape_pt_sequence" : 346,
    "shape_id" : "1B223DB9-78C8-4A42-8F3E-62EC9CB60AA7",
    "shape_pt_lon" : 23.882789000000002,
    "shape_pt_lat" : 42.347380999999984
  },
  {
    "shape_pt_sequence" : 347,
    "shape_id" : "1B223DB9-78C8-4A42-8F3E-62EC9CB60AA7",
    "shape_pt_lon" : 23.881669000000016,
    "shape_pt_lat" : 42.355360999999995
  },
  {
    "shape_pt_sequence" : 348,
    "shape_id" : "1B223DB9-78C8-4A42-8F3E-62EC9CB60AA7",
    "shape_pt_lon" : 23.883445999999992,
    "shape_pt_lat" : 42.363057999999988
  },
  {
    "shape_pt_sequence" : 349,
    "shape_id" : "1B223DB9-78C8-4A42-8F3E-62EC9CB60AA7",
    "shape_pt_lon" : 23.883764000000014,
    "shape_pt_lat" : 42.369505999999994
  },
  {
    "shape_pt_sequence" : 350,
    "shape_id" : "1B223DB9-78C8-4A42-8F3E-62EC9CB60AA7",
    "shape_pt_lon" : 23.854759000000001,
    "shape_pt_lat" : 42.39235399999999
  },
  {
    "shape_pt_sequence" : 351,
    "shape_id" : "1B223DB9-78C8-4A42-8F3E-62EC9CB60AA7",
    "shape_pt_lon" : 23.812907999999993,
    "shape_pt_lat" : 42.409989000000017
  },
  {
    "shape_pt_sequence" : 352,
    "shape_id" : "1B223DB9-78C8-4A42-8F3E-62EC9CB60AA7",
    "shape_pt_lon" : 23.797207000000043,
    "shape_pt_lat" : 42.430548000000002
  },
  {
    "shape_pt_sequence" : 353,
    "shape_id" : "1B223DB9-78C8-4A42-8F3E-62EC9CB60AA7",
    "shape_pt_lon" : 23.775480000000016,
    "shape_pt_lat" : 42.448583999999983
  },
  {
    "shape_pt_sequence" : 354,
    "shape_id" : "1B223DB9-78C8-4A42-8F3E-62EC9CB60AA7",
    "shape_pt_lon" : 23.766704000000033,
    "shape_pt_lat" : 42.471279999999993
  },
  {
    "shape_pt_sequence" : 355,
    "shape_id" : "1B223DB9-78C8-4A42-8F3E-62EC9CB60AA7",
    "shape_pt_lon" : 23.769631000000004,
    "shape_pt_lat" : 42.480114999999998
  },
  {
    "shape_pt_sequence" : 356,
    "shape_id" : "1B223DB9-78C8-4A42-8F3E-62EC9CB60AA7",
    "shape_pt_lon" : 23.77233099999998,
    "shape_pt_lat" : 42.487927999999989
  },
  {
    "shape_pt_sequence" : 357,
    "shape_id" : "1B223DB9-78C8-4A42-8F3E-62EC9CB60AA7",
    "shape_pt_lon" : 23.764331000000027,
    "shape_pt_lat" : 42.506405000000001
  },
  {
    "shape_pt_sequence" : 358,
    "shape_id" : "1B223DB9-78C8-4A42-8F3E-62EC9CB60AA7",
    "shape_pt_lon" : 23.752667000000002,
    "shape_pt_lat" : 42.512656999999983
  },
  {
    "shape_pt_sequence" : 359,
    "shape_id" : "1B223DB9-78C8-4A42-8F3E-62EC9CB60AA7",
    "shape_pt_lon" : 23.731830000000002,
    "shape_pt_lat" : 42.532389999999992
  },
  {
    "shape_pt_sequence" : 360,
    "shape_id" : "1B223DB9-78C8-4A42-8F3E-62EC9CB60AA7",
    "shape_pt_lon" : 23.725998000000004,
    "shape_pt_lat" : 42.538388000000005
  },
  {
    "shape_pt_sequence" : 361,
    "shape_id" : "1B223DB9-78C8-4A42-8F3E-62EC9CB60AA7",
    "shape_pt_lon" : 23.724457999999998,
    "shape_pt_lat" : 42.543674999999986
  },
  {
    "shape_pt_sequence" : 362,
    "shape_id" : "1B223DB9-78C8-4A42-8F3E-62EC9CB60AA7",
    "shape_pt_lon" : 23.711437000000018,
    "shape_pt_lat" : 42.552582999999998
  },
  {
    "shape_pt_sequence" : 363,
    "shape_id" : "1B223DB9-78C8-4A42-8F3E-62EC9CB60AA7",
    "shape_pt_lon" : 23.701186000000007,
    "shape_pt_lat" : 42.558616999999998
  },
  {
    "shape_pt_sequence" : 364,
    "shape_id" : "1B223DB9-78C8-4A42-8F3E-62EC9CB60AA7",
    "shape_pt_lon" : 23.677279000000027,
    "shape_pt_lat" : 42.567279999999997
  },
  {
    "shape_pt_sequence" : 365,
    "shape_id" : "1B223DB9-78C8-4A42-8F3E-62EC9CB60AA7",
    "shape_pt_lon" : 23.670892000000009,
    "shape_pt_lat" : 42.571154999999983
  },
  {
    "shape_pt_sequence" : 366,
    "shape_id" : "1B223DB9-78C8-4A42-8F3E-62EC9CB60AA7",
    "shape_pt_lon" : 23.672748000000013,
    "shape_pt_lat" : 42.576489000000009
  },
  {
    "shape_pt_sequence" : 367,
    "shape_id" : "1B223DB9-78C8-4A42-8F3E-62EC9CB60AA7",
    "shape_pt_lon" : 23.666734999999989,
    "shape_pt_lat" : 42.58332200000001
  },
  {
    "shape_pt_sequence" : 368,
    "shape_id" : "1B223DB9-78C8-4A42-8F3E-62EC9CB60AA7",
    "shape_pt_lon" : 23.664481999999992,
    "shape_pt_lat" : 42.586836999999989
  },
  {
    "shape_pt_sequence" : 369,
    "shape_id" : "1B223DB9-78C8-4A42-8F3E-62EC9CB60AA7",
    "shape_pt_lon" : 23.661530000000027,
    "shape_pt_lat" : 42.595703999999991
  },
  {
    "shape_pt_sequence" : 370,
    "shape_id" : "1B223DB9-78C8-4A42-8F3E-62EC9CB60AA7",
    "shape_pt_lon" : 23.650578999999993,
    "shape_pt_lat" : 42.600090000000002
  },
  {
    "shape_pt_sequence" : 371,
    "shape_id" : "1B223DB9-78C8-4A42-8F3E-62EC9CB60AA7",
    "shape_pt_lon" : 23.642109000000005,
    "shape_pt_lat" : 42.596632999999997
  },
  {
    "shape_pt_sequence" : 372,
    "shape_id" : "1B223DB9-78C8-4A42-8F3E-62EC9CB60AA7",
    "shape_pt_lon" : 23.637754000000001,
    "shape_pt_lat" : 42.598860999999999
  },
  {
    "shape_pt_sequence" : 373,
    "shape_id" : "1B223DB9-78C8-4A42-8F3E-62EC9CB60AA7",
    "shape_pt_lon" : 23.636462000000023,
    "shape_pt_lat" : 42.61089599999999
  },
  {
    "shape_pt_sequence" : 374,
    "shape_id" : "1B223DB9-78C8-4A42-8F3E-62EC9CB60AA7",
    "shape_pt_lon" : 23.627569999999992,
    "shape_pt_lat" : 42.617713999999992
  },
  {
    "shape_pt_sequence" : 375,
    "shape_id" : "1B223DB9-78C8-4A42-8F3E-62EC9CB60AA7",
    "shape_pt_lon" : 23.57396,
    "shape_pt_lat" : 42.629631000000003
  },
  {
    "shape_pt_sequence" : 376,
    "shape_id" : "1B223DB9-78C8-4A42-8F3E-62EC9CB60AA7",
    "shape_pt_lon" : 23.476162999999985,
    "shape_pt_lat" : 42.650909999999996
  },
  {
    "shape_pt_sequence" : 377,
    "shape_id" : "1B223DB9-78C8-4A42-8F3E-62EC9CB60AA7",
    "shape_pt_lon" : 23.424772999999988,
    "shape_pt_lat" : 42.662029000000004
  },
  {
    "shape_pt_sequence" : 378,
    "shape_id" : "1B223DB9-78C8-4A42-8F3E-62EC9CB60AA7",
    "shape_pt_lon" : 23.410627000000005,
    "shape_pt_lat" : 42.665574999999983
  },
  {
    "shape_pt_sequence" : 379,
    "shape_id" : "1B223DB9-78C8-4A42-8F3E-62EC9CB60AA7",
    "shape_pt_lon" : 23.390320000000003,
    "shape_pt_lat" : 42.678273000000004
  },
  {
    "shape_pt_sequence" : 380,
    "shape_id" : "1B223DB9-78C8-4A42-8F3E-62EC9CB60AA7",
    "shape_pt_lon" : 23.361102000000017,
    "shape_pt_lat" : 42.696727000000003
  },
  {
    "shape_pt_sequence" : 381,
    "shape_id" : "1B223DB9-78C8-4A42-8F3E-62EC9CB60AA7",
    "shape_pt_lon" : 23.343273000000011,
    "shape_pt_lat" : 42.701165000000003
  },
  {
    "shape_pt_sequence" : 382,
    "shape_id" : "1B223DB9-78C8-4A42-8F3E-62EC9CB60AA7",
    "shape_pt_lon" : 23.330246000000017,
    "shape_pt_lat" : 42.709219000000004
  },
  {
    "shape_pt_sequence" : 383,
    "shape_id" : "1B223DB9-78C8-4A42-8F3E-62EC9CB60AA7",
    "shape_pt_lon" : 23.321003999999988,
    "shape_pt_lat" : 42.712436999999994
  },
  {
    "shape_pt_sequence" : 384,
    "shape_id" : "1B223DB9-78C8-4A42-8F3E-62EC9CB60AA7",
    "shape_pt_lon" : 23.321003999999988,
    "shape_pt_lat" : 42.712436999999994
  },
  {
    "shape_pt_sequence" : 385,
    "shape_id" : "1B223DB9-78C8-4A42-8F3E-62EC9CB60AA7",
    "shape_pt_lon" : 23.321003999999988,
    "shape_pt_lat" : 42.712436999999994
  },
  {
    "shape_pt_sequence" : 386,
    "shape_id" : "1B223DB9-78C8-4A42-8F3E-62EC9CB60AA7",
    "shape_pt_lon" : 23.309004999999985,
    "shape_pt_lat" : 42.717312
  },
  {
    "shape_pt_sequence" : 387,
    "shape_id" : "1B223DB9-78C8-4A42-8F3E-62EC9CB60AA7",
    "shape_pt_lon" : 23.296165000000002,
    "shape_pt_lat" : 42.722467000000002
  },
  {
    "shape_pt_sequence" : 388,
    "shape_id" : "1B223DB9-78C8-4A42-8F3E-62EC9CB60AA7",
    "shape_pt_lon" : 23.272054000000026,
    "shape_pt_lat" : 42.732394999999983
  },
  {
    "shape_pt_sequence" : 389,
    "shape_id" : "1B223DB9-78C8-4A42-8F3E-62EC9CB60AA7",
    "shape_pt_lon" : 23.264225000000039,
    "shape_pt_lat" : 42.738151999999999
  },
  {
    "shape_pt_sequence" : 390,
    "shape_id" : "1B223DB9-78C8-4A42-8F3E-62EC9CB60AA7",
    "shape_pt_lon" : 23.247628999999989,
    "shape_pt_lat" : 42.752471999999997
  },
  {
    "shape_pt_sequence" : 391,
    "shape_id" : "1B223DB9-78C8-4A42-8F3E-62EC9CB60AA7",
    "shape_pt_lon" : 23.222913000000005,
    "shape_pt_lat" : 42.772888999999992
  },
  {
    "shape_pt_sequence" : 392,
    "shape_id" : "1B223DB9-78C8-4A42-8F3E-62EC9CB60AA7",
    "shape_pt_lon" : 23.209626000000043,
    "shape_pt_lat" : 42.79238999999999
  },
  {
    "shape_pt_sequence" : 393,
    "shape_id" : "1B223DB9-78C8-4A42-8F3E-62EC9CB60AA7",
    "shape_pt_lon" : 23.199838000000028,
    "shape_pt_lat" : 42.806620999999986
  },
  {
    "shape_pt_sequence" : 394,
    "shape_id" : "1B223DB9-78C8-4A42-8F3E-62EC9CB60AA7",
    "shape_pt_lon" : 23.193207000000001,
    "shape_pt_lat" : 42.810987000000011
  },
  {
    "shape_pt_sequence" : 395,
    "shape_id" : "1B223DB9-78C8-4A42-8F3E-62EC9CB60AA7",
    "shape_pt_lon" : 23.126044000000036,
    "shape_pt_lat" : 42.826597
  },
  {
    "shape_pt_sequence" : 396,
    "shape_id" : "1B223DB9-78C8-4A42-8F3E-62EC9CB60AA7",
    "shape_pt_lon" : 23.092786000000018,
    "shape_pt_lat" : 42.834386999999992
  },
  {
    "shape_pt_sequence" : 397,
    "shape_id" : "1B223DB9-78C8-4A42-8F3E-62EC9CB60AA7",
    "shape_pt_lon" : 23.068306000000035,
    "shape_pt_lat" : 42.845481000000007
  },
  {
    "shape_pt_sequence" : 398,
    "shape_id" : "1B223DB9-78C8-4A42-8F3E-62EC9CB60AA7",
    "shape_pt_lon" : 23.039759000000032,
    "shape_pt_lat" : 42.854690999999995
  },
  {
    "shape_pt_sequence" : 399,
    "shape_id" : "1B223DB9-78C8-4A42-8F3E-62EC9CB60AA7",
    "shape_pt_lon" : 23.027989999999988,
    "shape_pt_lat" : 42.864462000000003
  },
  {
    "shape_pt_sequence" : 400,
    "shape_id" : "1B223DB9-78C8-4A42-8F3E-62EC9CB60AA7",
    "shape_pt_lon" : 23.019328999999999,
    "shape_pt_lat" : 42.867424999999983
  },
  {
    "shape_pt_sequence" : 401,
    "shape_id" : "1B223DB9-78C8-4A42-8F3E-62EC9CB60AA7",
    "shape_pt_lon" : 23.015760999999998,
    "shape_pt_lat" : 42.875554999999999
  },
  {
    "shape_pt_sequence" : 402,
    "shape_id" : "1B223DB9-78C8-4A42-8F3E-62EC9CB60AA7",
    "shape_pt_lon" : 23.016031999999996,
    "shape_pt_lat" : 42.880083000000006
  },
  {
    "shape_pt_sequence" : 403,
    "shape_id" : "1B223DB9-78C8-4A42-8F3E-62EC9CB60AA7",
    "shape_pt_lon" : 23.00065699999999,
    "shape_pt_lat" : 42.880334999999995
  },
  {
    "shape_pt_sequence" : 404,
    "shape_id" : "1B223DB9-78C8-4A42-8F3E-62EC9CB60AA7",
    "shape_pt_lon" : 22.98744099999999,
    "shape_pt_lat" : 42.879564999999992
  },
  {
    "shape_pt_sequence" : 405,
    "shape_id" : "1B223DB9-78C8-4A42-8F3E-62EC9CB60AA7",
    "shape_pt_lon" : 22.972969000000006,
    "shape_pt_lat" : 42.892048000000003
  },
  {
    "shape_pt_sequence" : 406,
    "shape_id" : "1B223DB9-78C8-4A42-8F3E-62EC9CB60AA7",
    "shape_pt_lon" : 22.953682000000043,
    "shape_pt_lat" : 42.899257999999989
  },
  {
    "shape_pt_sequence" : 407,
    "shape_id" : "1B223DB9-78C8-4A42-8F3E-62EC9CB60AA7",
    "shape_pt_lon" : 22.945062000000007,
    "shape_pt_lat" : 42.907239000000004
  },
  {
    "shape_pt_sequence" : 408,
    "shape_id" : "1B223DB9-78C8-4A42-8F3E-62EC9CB60AA7",
    "shape_pt_lon" : 22.934649000000036,
    "shape_pt_lat" : 42.915886000000015
  },
  {
    "shape_pt_sequence" : 409,
    "shape_id" : "1B223DB9-78C8-4A42-8F3E-62EC9CB60AA7",
    "shape_pt_lon" : 22.930263999999994,
    "shape_pt_lat" : 42.91841999999999
  },
  {
    "shape_pt_sequence" : 410,
    "shape_id" : "1B223DB9-78C8-4A42-8F3E-62EC9CB60AA7",
    "shape_pt_lon" : 22.931940999999995,
    "shape_pt_lat" : 42.92213499999999
  },
  {
    "shape_pt_sequence" : 411,
    "shape_id" : "1B223DB9-78C8-4A42-8F3E-62EC9CB60AA7",
    "shape_pt_lon" : 22.931940999999995,
    "shape_pt_lat" : 42.92213499999999
  },
  {
    "shape_pt_sequence" : 412,
    "shape_id" : "1B223DB9-78C8-4A42-8F3E-62EC9CB60AA7",
    "shape_pt_lon" : 22.931940000000026,
    "shape_pt_lat" : 42.92213499999999
  },
  {
    "shape_pt_sequence" : 413,
    "shape_id" : "1B223DB9-78C8-4A42-8F3E-62EC9CB60AA7",
    "shape_pt_lon" : 22.931940000000026,
    "shape_pt_lat" : 42.92213499999999
  },
  {
    "shape_pt_sequence" : 414,
    "shape_id" : "1B223DB9-78C8-4A42-8F3E-62EC9CB60AA7",
    "shape_pt_lon" : 22.933097000000004,
    "shape_pt_lat" : 42.926605000000009
  },
  {
    "shape_pt_sequence" : 415,
    "shape_id" : "1B223DB9-78C8-4A42-8F3E-62EC9CB60AA7",
    "shape_pt_lon" : 22.930703999999992,
    "shape_pt_lat" : 42.92953399999999
  },
  {
    "shape_pt_sequence" : 416,
    "shape_id" : "1B223DB9-78C8-4A42-8F3E-62EC9CB60AA7",
    "shape_pt_lon" : 22.916904999999986,
    "shape_pt_lat" : 42.930789000000011
  },
  {
    "shape_pt_sequence" : 417,
    "shape_id" : "1B223DB9-78C8-4A42-8F3E-62EC9CB60AA7",
    "shape_pt_lon" : 22.904429999999962,
    "shape_pt_lat" : 42.932946999999992
  },
  {
    "shape_pt_sequence" : 418,
    "shape_id" : "1B223DB9-78C8-4A42-8F3E-62EC9CB60AA7",
    "shape_pt_lon" : 22.9024,
    "shape_pt_lat" : 42.938870999999999
  },
  {
    "shape_pt_sequence" : 419,
    "shape_id" : "1B223DB9-78C8-4A42-8F3E-62EC9CB60AA7",
    "shape_pt_lon" : 22.901046000000036,
    "shape_pt_lat" : 42.94669099999998
  },
  {
    "shape_pt_sequence" : 420,
    "shape_id" : "1B223DB9-78C8-4A42-8F3E-62EC9CB60AA7",
    "shape_pt_lon" : 22.904676999999992,
    "shape_pt_lat" : 42.953069999999975
  },
  {
    "shape_pt_sequence" : 421,
    "shape_id" : "1B223DB9-78C8-4A42-8F3E-62EC9CB60AA7",
    "shape_pt_lon" : 22.902610000000038,
    "shape_pt_lat" : 42.958434999999994
  },
  {
    "shape_pt_sequence" : 422,
    "shape_id" : "1B223DB9-78C8-4A42-8F3E-62EC9CB60AA7",
    "shape_pt_lon" : 22.892268000000001,
    "shape_pt_lat" : 42.962037000000002
  },
  {
    "shape_pt_sequence" : 423,
    "shape_id" : "1B223DB9-78C8-4A42-8F3E-62EC9CB60AA7",
    "shape_pt_lon" : 22.885020000000026,
    "shape_pt_lat" : 42.963186
  },
  {
    "shape_pt_sequence" : 424,
    "shape_id" : "1B223DB9-78C8-4A42-8F3E-62EC9CB60AA7",
    "shape_pt_lon" : 22.876903999999996,
    "shape_pt_lat" : 42.964075999999991
  },
  {
    "shape_pt_sequence" : 425,
    "shape_id" : "1B223DB9-78C8-4A42-8F3E-62EC9CB60AA7",
    "shape_pt_lon" : 22.86716899999999,
    "shape_pt_lat" : 42.966757000000001
  },
  {
    "shape_pt_sequence" : 426,
    "shape_id" : "1B223DB9-78C8-4A42-8F3E-62EC9CB60AA7",
    "shape_pt_lon" : 22.859266000000019,
    "shape_pt_lat" : 42.970027999999992
  },
  {
    "shape_pt_sequence" : 427,
    "shape_id" : "1B223DB9-78C8-4A42-8F3E-62EC9CB60AA7",
    "shape_pt_lon" : 22.851517999999999,
    "shape_pt_lat" : 42.972816999999985
  },
  {
    "shape_pt_sequence" : 428,
    "shape_id" : "1B223DB9-78C8-4A42-8F3E-62EC9CB60AA7",
    "shape_pt_lon" : 22.848953999999992,
    "shape_pt_lat" : 42.976216999999998
  },
  {
    "shape_pt_sequence" : 429,
    "shape_id" : "1B223DB9-78C8-4A42-8F3E-62EC9CB60AA7",
    "shape_pt_lon" : 22.849938000000009,
    "shape_pt_lat" : 42.982762000000008
  },
  {
    "shape_pt_sequence" : 430,
    "shape_id" : "1B223DB9-78C8-4A42-8F3E-62EC9CB60AA7",
    "shape_pt_lon" : 22.851553999999965,
    "shape_pt_lat" : 42.990831999999997
  },
  {
    "shape_pt_sequence" : 431,
    "shape_id" : "1B223DB9-78C8-4A42-8F3E-62EC9CB60AA7",
    "shape_pt_lon" : 22.847352000000029,
    "shape_pt_lat" : 42.993268000000008
  },
  {
    "shape_pt_sequence" : 432,
    "shape_id" : "1B223DB9-78C8-4A42-8F3E-62EC9CB60AA7",
    "shape_pt_lon" : 22.837795999999997,
    "shape_pt_lat" : 42.997478999999991
  },
  {
    "shape_pt_sequence" : 433,
    "shape_id" : "1B223DB9-78C8-4A42-8F3E-62EC9CB60AA7",
    "shape_pt_lon" : 22.819529000000017,
    "shape_pt_lat" : 43.002863000000005
  },
  {
    "shape_pt_sequence" : 434,
    "shape_id" : "1B223DB9-78C8-4A42-8F3E-62EC9CB60AA7",
    "shape_pt_lon" : 22.804234000000008,
    "shape_pt_lat" : 43.00773199999999
  },
  {
    "shape_pt_sequence" : 435,
    "shape_id" : "1B223DB9-78C8-4A42-8F3E-62EC9CB60AA7",
    "shape_pt_lon" : 22.797223000000002,
    "shape_pt_lat" : 43.013287000000005
  },
  {
    "shape_pt_sequence" : 436,
    "shape_id" : "1B223DB9-78C8-4A42-8F3E-62EC9CB60AA7",
    "shape_pt_lon" : 22.787131000000016,
    "shape_pt_lat" : 43.016000999999989
  },
  {
    "shape_pt_sequence" : 437,
    "shape_id" : "1B223DB9-78C8-4A42-8F3E-62EC9CB60AA7",
    "shape_pt_lon" : 22.775693999999987,
    "shape_pt_lat" : 43.015653
  },
  {
    "shape_pt_sequence" : 438,
    "shape_id" : "1B223DB9-78C8-4A42-8F3E-62EC9CB60AA7",
    "shape_pt_lon" : 22.76681099999999,
    "shape_pt_lat" : 43.011586999999992
  },
  {
    "shape_pt_sequence" : 439,
    "shape_id" : "1B223DB9-78C8-4A42-8F3E-62EC9CB60AA7",
    "shape_pt_lon" : 22.76681099999999,
    "shape_pt_lat" : 43.011586999999992
  },
  {
    "shape_pt_sequence" : 440,
    "shape_id" : "1B223DB9-78C8-4A42-8F3E-62EC9CB60AA7",
    "shape_pt_lon" : 22.766809999999964,
    "shape_pt_lat" : 43.011586999999992
  },
  {
    "shape_pt_sequence" : 441,
    "shape_id" : "1B223DB9-78C8-4A42-8F3E-62EC9CB60AA7",
    "shape_pt_lon" : 22.761044999999996,
    "shape_pt_lat" : 43.010110000000005
  },
  {
    "shape_pt_sequence" : 442,
    "shape_id" : "1B223DB9-78C8-4A42-8F3E-62EC9CB60AA7",
    "shape_pt_lon" : 22.748830999999996,
    "shape_pt_lat" : 43.010978999999999
  },
  {
    "shape_pt_sequence" : 443,
    "shape_id" : "1B223DB9-78C8-4A42-8F3E-62EC9CB60AA7",
    "shape_pt_lon" : 22.726003999999961,
    "shape_pt_lat" : 43.021698000000008
  },
  {
    "shape_pt_sequence" : 444,
    "shape_id" : "1B223DB9-78C8-4A42-8F3E-62EC9CB60AA7",
    "shape_pt_lon" : 22.717269000000016,
    "shape_pt_lat" : 43.034578999999994
  },
  {
    "shape_pt_sequence" : 445,
    "shape_id" : "1B223DB9-78C8-4A42-8F3E-62EC9CB60AA7",
    "shape_pt_lon" : 22.694498000000038,
    "shape_pt_lat" : 43.055979999999991
  },
  {
    "shape_pt_sequence" : 446,
    "shape_id" : "1B223DB9-78C8-4A42-8F3E-62EC9CB60AA7",
    "shape_pt_lon" : 22.682116000000008,
    "shape_pt_lat" : 43.060425999999978
  },
  {
    "shape_pt_sequence" : 447,
    "shape_id" : "1B223DB9-78C8-4A42-8F3E-62EC9CB60AA7",
    "shape_pt_lon" : 22.640381999999988,
    "shape_pt_lat" : 43.098740999999997
  },
  {
    "shape_pt_sequence" : 448,
    "shape_id" : "1B223DB9-78C8-4A42-8F3E-62EC9CB60AA7",
    "shape_pt_lon" : 22.599522000000036,
    "shape_pt_lat" : 43.14100899999999
  },
  {
    "shape_pt_sequence" : 449,
    "shape_id" : "1B223DB9-78C8-4A42-8F3E-62EC9CB60AA7",
    "shape_pt_lon" : 22.599419000000012,
    "shape_pt_lat" : 43.149739000000004
  },
  {
    "shape_pt_sequence" : 450,
    "shape_id" : "1B223DB9-78C8-4A42-8F3E-62EC9CB60AA7",
    "shape_pt_lon" : 22.601416999999998,
    "shape_pt_lat" : 43.157963999999993
  },
  {
    "shape_pt_sequence" : 451,
    "shape_id" : "1B223DB9-78C8-4A42-8F3E-62EC9CB60AA7",
    "shape_pt_lon" : 22.599712000000039,
    "shape_pt_lat" : 43.161377999999992
  },
  {
    "shape_pt_sequence" : 452,
    "shape_id" : "1B223DB9-78C8-4A42-8F3E-62EC9CB60AA7",
    "shape_pt_lon" : 22.591422999999992,
    "shape_pt_lat" : 43.165770000000002
  },
  {
    "shape_pt_sequence" : 453,
    "shape_id" : "1B223DB9-78C8-4A42-8F3E-62EC9CB60AA7",
    "shape_pt_lon" : 22.586467999999996,
    "shape_pt_lat" : 43.169913999999991
  },
  {
    "shape_pt_sequence" : 454,
    "shape_id" : "1B223DB9-78C8-4A42-8F3E-62EC9CB60AA7",
    "shape_pt_lon" : 22.586467999999996,
    "shape_pt_lat" : 43.169913999999991
  },
  {
    "shape_pt_sequence" : 455,
    "shape_id" : "1B223DB9-78C8-4A42-8F3E-62EC9CB60AA7",
    "shape_pt_lon" : 22.586467999999996,
    "shape_pt_lat" : 43.169913999999991
  },
  {
    "shape_pt_sequence" : 456,
    "shape_id" : "1B223DB9-78C8-4A42-8F3E-62EC9CB60AA7",
    "shape_pt_lon" : 22.582326000000023,
    "shape_pt_lat" : 43.175144000000003
  },
  {
    "shape_pt_sequence" : 457,
    "shape_id" : "1B223DB9-78C8-4A42-8F3E-62EC9CB60AA7",
    "shape_pt_lon" : 22.569727,
    "shape_pt_lat" : 43.187037999999994
  },
  {
    "shape_pt_sequence" : 458,
    "shape_id" : "1B223DB9-78C8-4A42-8F3E-62EC9CB60AA7",
    "shape_pt_lon" : 22.557334999999995,
    "shape_pt_lat" : 43.205876000000004
  },
  {
    "shape_pt_sequence" : 459,
    "shape_id" : "1B223DB9-78C8-4A42-8F3E-62EC9CB60AA7",
    "shape_pt_lon" : 22.555067000000037,
    "shape_pt_lat" : 43.212049
  },
  {
    "shape_pt_sequence" : 460,
    "shape_id" : "1B223DB9-78C8-4A42-8F3E-62EC9CB60AA7",
    "shape_pt_lon" : 22.547380000000004,
    "shape_pt_lat" : 43.213802000000001
  },
  {
    "shape_pt_sequence" : 461,
    "shape_id" : "1B223DB9-78C8-4A42-8F3E-62EC9CB60AA7",
    "shape_pt_lon" : 22.541751000000005,
    "shape_pt_lat" : 43.216622999999998
  },
  {
    "shape_pt_sequence" : 462,
    "shape_id" : "1B223DB9-78C8-4A42-8F3E-62EC9CB60AA7",
    "shape_pt_lon" : 22.533904000000035,
    "shape_pt_lat" : 43.215237000000002
  },
  {
    "shape_pt_sequence" : 463,
    "shape_id" : "1B223DB9-78C8-4A42-8F3E-62EC9CB60AA7",
    "shape_pt_lon" : 22.512847999999991,
    "shape_pt_lat" : 43.213235000000005
  },
  {
    "shape_pt_sequence" : 464,
    "shape_id" : "1B223DB9-78C8-4A42-8F3E-62EC9CB60AA7",
    "shape_pt_lon" : 22.503630999999984,
    "shape_pt_lat" : 43.214016000000001
  },
  {
    "shape_pt_sequence" : 465,
    "shape_id" : "1B223DB9-78C8-4A42-8F3E-62EC9CB60AA7",
    "shape_pt_lon" : 22.494304,
    "shape_pt_lat" : 43.219935999999983
  },
  {
    "shape_pt_sequence" : 466,
    "shape_id" : "1B223DB9-78C8-4A42-8F3E-62EC9CB60AA7",
    "shape_pt_lon" : 22.476036000000022,
    "shape_pt_lat" : 43.221679999999992
  },
  {
    "shape_pt_sequence" : 467,
    "shape_id" : "1B223DB9-78C8-4A42-8F3E-62EC9CB60AA7",
    "shape_pt_lon" : 22.463376000000011,
    "shape_pt_lat" : 43.228376999999988
  },
  {
    "shape_pt_sequence" : 468,
    "shape_id" : "1B223DB9-78C8-4A42-8F3E-62EC9CB60AA7",
    "shape_pt_lon" : 22.453292000000033,
    "shape_pt_lat" : 43.232941999999987
  },
  {
    "shape_pt_sequence" : 469,
    "shape_id" : "1B223DB9-78C8-4A42-8F3E-62EC9CB60AA7",
    "shape_pt_lon" : 22.435851000000014,
    "shape_pt_lat" : 43.228489000000003
  },
  {
    "shape_pt_sequence" : 470,
    "shape_id" : "1B223DB9-78C8-4A42-8F3E-62EC9CB60AA7",
    "shape_pt_lon" : 22.432209000000029,
    "shape_pt_lat" : 43.224359999999983
  },
  {
    "shape_pt_sequence" : 471,
    "shape_id" : "1B223DB9-78C8-4A42-8F3E-62EC9CB60AA7",
    "shape_pt_lon" : 22.418329000000028,
    "shape_pt_lat" : 43.218799000000004
  },
  {
    "shape_pt_sequence" : 472,
    "shape_id" : "1B223DB9-78C8-4A42-8F3E-62EC9CB60AA7",
    "shape_pt_lon" : 22.411966000000007,
    "shape_pt_lat" : 43.218854999999991
  },
  {
    "shape_pt_sequence" : 473,
    "shape_id" : "1B223DB9-78C8-4A42-8F3E-62EC9CB60AA7",
    "shape_pt_lon" : 22.408299,
    "shape_pt_lat" : 43.228380000000008
  },
  {
    "shape_pt_sequence" : 474,
    "shape_id" : "1B223DB9-78C8-4A42-8F3E-62EC9CB60AA7",
    "shape_pt_lon" : 22.404369000000003,
    "shape_pt_lat" : 43.230753
  },
  {
    "shape_pt_sequence" : 475,
    "shape_id" : "1B223DB9-78C8-4A42-8F3E-62EC9CB60AA7",
    "shape_pt_lon" : 22.394654000000031,
    "shape_pt_lat" : 43.229261999999999
  },
  {
    "shape_pt_sequence" : 476,
    "shape_id" : "1B223DB9-78C8-4A42-8F3E-62EC9CB60AA7",
    "shape_pt_lon" : 22.382295000000028,
    "shape_pt_lat" : 43.230391999999995
  },
  {
    "shape_pt_sequence" : 477,
    "shape_id" : "1B223DB9-78C8-4A42-8F3E-62EC9CB60AA7",
    "shape_pt_lon" : 22.37599800000001,
    "shape_pt_lat" : 43.234102
  },
  {
    "shape_pt_sequence" : 478,
    "shape_id" : "1B223DB9-78C8-4A42-8F3E-62EC9CB60AA7",
    "shape_pt_lon" : 22.358041000000014,
    "shape_pt_lat" : 43.225158999999984
  },
  {
    "shape_pt_sequence" : 479,
    "shape_id" : "1B223DB9-78C8-4A42-8F3E-62EC9CB60AA7",
    "shape_pt_lon" : 22.335835000000031,
    "shape_pt_lat" : 43.223340999999998
  },
  {
    "shape_pt_sequence" : 480,
    "shape_id" : "1B223DB9-78C8-4A42-8F3E-62EC9CB60AA7",
    "shape_pt_lon" : 22.317642000000006,
    "shape_pt_lat" : 43.221625000000003
  },
  {
    "shape_pt_sequence" : 481,
    "shape_id" : "1B223DB9-78C8-4A42-8F3E-62EC9CB60AA7",
    "shape_pt_lon" : 22.317642000000006,
    "shape_pt_lat" : 43.221625000000003
  },
  {
    "shape_pt_sequence" : 482,
    "shape_id" : "1B223DB9-78C8-4A42-8F3E-62EC9CB60AA7",
    "shape_pt_lon" : 22.317644999999999,
    "shape_pt_lat" : 43.221637000000001
  },
  {
    "shape_pt_sequence" : 483,
    "shape_id" : "1B223DB9-78C8-4A42-8F3E-62EC9CB60AA7",
    "shape_pt_lon" : 21.896329999999999,
    "shape_pt_lat" : 43.319380000000002
  },
  {
    "shape_pt_sequence" : 484,
    "shape_id" : "1B223DB9-78C8-4A42-8F3E-62EC9CB60AA7",
    "shape_pt_lon" : 21.896329999999999,
    "shape_pt_lat" : 43.319380000000002
  },
  {
    "shape_pt_sequence" : 485,
    "shape_id" : "1B223DB9-78C8-4A42-8F3E-62EC9CB60AA7",
    "shape_pt_lon" : 21.41658,
    "shape_pt_lat" : 43.861590999999997
  },
  {
    "shape_pt_sequence" : 486,
    "shape_id" : "1B223DB9-78C8-4A42-8F3E-62EC9CB60AA7",
    "shape_pt_lon" : 21.41658,
    "shape_pt_lat" : 43.861590999999997
  },
  {
    "shape_pt_sequence" : 487,
    "shape_id" : "1B223DB9-78C8-4A42-8F3E-62EC9CB60AA7",
    "shape_pt_lon" : 21.263263999999999,
    "shape_pt_lat" : 43.982205
  },
  {
    "shape_pt_sequence" : 488,
    "shape_id" : "1B223DB9-78C8-4A42-8F3E-62EC9CB60AA7",
    "shape_pt_lon" : 21.263276999999988,
    "shape_pt_lat" : 43.982218000000003
  },
  {
    "shape_pt_sequence" : 489,
    "shape_id" : "1B223DB9-78C8-4A42-8F3E-62EC9CB60AA7",
    "shape_pt_lon" : 21.263276999999988,
    "shape_pt_lat" : 43.982218000000003
  },
  {
    "shape_pt_sequence" : 490,
    "shape_id" : "1B223DB9-78C8-4A42-8F3E-62EC9CB60AA7",
    "shape_pt_lon" : 21.251945000000035,
    "shape_pt_lat" : 43.988099999999996
  },
  {
    "shape_pt_sequence" : 491,
    "shape_id" : "1B223DB9-78C8-4A42-8F3E-62EC9CB60AA7",
    "shape_pt_lon" : 21.239426000000009,
    "shape_pt_lat" : 43.995350000000002
  },
  {
    "shape_pt_sequence" : 492,
    "shape_id" : "1B223DB9-78C8-4A42-8F3E-62EC9CB60AA7",
    "shape_pt_lon" : 21.236539999999991,
    "shape_pt_lat" : 44.001635999999991
  },
  {
    "shape_pt_sequence" : 493,
    "shape_id" : "1B223DB9-78C8-4A42-8F3E-62EC9CB60AA7",
    "shape_pt_lon" : 21.229930999999993,
    "shape_pt_lat" : 44.012949000000006
  },
  {
    "shape_pt_sequence" : 494,
    "shape_id" : "1B223DB9-78C8-4A42-8F3E-62EC9CB60AA7",
    "shape_pt_lon" : 21.22750099999999,
    "shape_pt_lat" : 44.021994999999983
  },
  {
    "shape_pt_sequence" : 495,
    "shape_id" : "1B223DB9-78C8-4A42-8F3E-62EC9CB60AA7",
    "shape_pt_lon" : 21.236437999999993,
    "shape_pt_lat" : 44.028540999999983
  },
  {
    "shape_pt_sequence" : 496,
    "shape_id" : "1B223DB9-78C8-4A42-8F3E-62EC9CB60AA7",
    "shape_pt_lon" : 21.236437999999993,
    "shape_pt_lat" : 44.042524999999983
  },
  {
    "shape_pt_sequence" : 497,
    "shape_id" : "1B223DB9-78C8-4A42-8F3E-62EC9CB60AA7",
    "shape_pt_lon" : 21.233895000000018,
    "shape_pt_lat" : 44.051323999999994
  },
  {
    "shape_pt_sequence" : 498,
    "shape_id" : "1B223DB9-78C8-4A42-8F3E-62EC9CB60AA7",
    "shape_pt_lon" : 21.204618000000039,
    "shape_pt_lat" : 44.062797000000003
  },
  {
    "shape_pt_sequence" : 499,
    "shape_id" : "1B223DB9-78C8-4A42-8F3E-62EC9CB60AA7",
    "shape_pt_lon" : 21.189190999999994,
    "shape_pt_lat" : 44.077033999999998
  },
  {
    "shape_pt_sequence" : 500,
    "shape_id" : "1B223DB9-78C8-4A42-8F3E-62EC9CB60AA7",
    "shape_pt_lon" : 21.183773000000002,
    "shape_pt_lat" : 44.081156
  },
  {
    "shape_pt_sequence" : 501,
    "shape_id" : "1B223DB9-78C8-4A42-8F3E-62EC9CB60AA7",
    "shape_pt_lon" : 21.166498999999988,
    "shape_pt_lat" : 44.091682000000006
  },
  {
    "shape_pt_sequence" : 502,
    "shape_id" : "1B223DB9-78C8-4A42-8F3E-62EC9CB60AA7",
    "shape_pt_lon" : 21.165267,
    "shape_pt_lat" : 44.095744999999994
  },
  {
    "shape_pt_sequence" : 503,
    "shape_id" : "1B223DB9-78C8-4A42-8F3E-62EC9CB60AA7",
    "shape_pt_lon" : 21.165885000000003,
    "shape_pt_lat" : 44.102108999999999
  },
  {
    "shape_pt_sequence" : 504,
    "shape_id" : "1B223DB9-78C8-4A42-8F3E-62EC9CB60AA7",
    "shape_pt_lon" : 21.161327000000028,
    "shape_pt_lat" : 44.106619000000009
  },
  {
    "shape_pt_sequence" : 505,
    "shape_id" : "1B223DB9-78C8-4A42-8F3E-62EC9CB60AA7",
    "shape_pt_lon" : 21.133350000000007,
    "shape_pt_lat" : 44.125723999999991
  },
  {
    "shape_pt_sequence" : 506,
    "shape_id" : "1B223DB9-78C8-4A42-8F3E-62EC9CB60AA7",
    "shape_pt_lon" : 21.106409000000014,
    "shape_pt_lat" : 44.151268000000002
  },
  {
    "shape_pt_sequence" : 507,
    "shape_id" : "1B223DB9-78C8-4A42-8F3E-62EC9CB60AA7",
    "shape_pt_lon" : 21.098488000000032,
    "shape_pt_lat" : 44.163902
  },
  {
    "shape_pt_sequence" : 508,
    "shape_id" : "1B223DB9-78C8-4A42-8F3E-62EC9CB60AA7",
    "shape_pt_lon" : 21.103036000000031,
    "shape_pt_lat" : 44.184050999999997
  },
  {
    "shape_pt_sequence" : 509,
    "shape_id" : "1B223DB9-78C8-4A42-8F3E-62EC9CB60AA7",
    "shape_pt_lon" : 21.09348300000002,
    "shape_pt_lat" : 44.205961000000009
  },
  {
    "shape_pt_sequence" : 510,
    "shape_id" : "1B223DB9-78C8-4A42-8F3E-62EC9CB60AA7",
    "shape_pt_lon" : 21.093694999999997,
    "shape_pt_lat" : 44.212786000000001
  },
  {
    "shape_pt_sequence" : 511,
    "shape_id" : "1B223DB9-78C8-4A42-8F3E-62EC9CB60AA7",
    "shape_pt_lon" : 21.097249000000033,
    "shape_pt_lat" : 44.248457999999985
  },
  {
    "shape_pt_sequence" : 512,
    "shape_id" : "1B223DB9-78C8-4A42-8F3E-62EC9CB60AA7",
    "shape_pt_lon" : 21.093707999999992,
    "shape_pt_lat" : 44.255735999999992
  },
  {
    "shape_pt_sequence" : 513,
    "shape_id" : "1B223DB9-78C8-4A42-8F3E-62EC9CB60AA7",
    "shape_pt_lon" : 21.09081900000001,
    "shape_pt_lat" : 44.269911000000008
  },
  {
    "shape_pt_sequence" : 514,
    "shape_id" : "1B223DB9-78C8-4A42-8F3E-62EC9CB60AA7",
    "shape_pt_lon" : 21.092669000000001,
    "shape_pt_lat" : 44.286625999999984
  },
  {
    "shape_pt_sequence" : 515,
    "shape_id" : "1B223DB9-78C8-4A42-8F3E-62EC9CB60AA7",
    "shape_pt_lon" : 21.085927999999996,
    "shape_pt_lat" : 44.300916999999984
  },
  {
    "shape_pt_sequence" : 516,
    "shape_id" : "1B223DB9-78C8-4A42-8F3E-62EC9CB60AA7",
    "shape_pt_lon" : 21.083092000000022,
    "shape_pt_lat" : 44.30974599999999
  },
  {
    "shape_pt_sequence" : 517,
    "shape_id" : "1B223DB9-78C8-4A42-8F3E-62EC9CB60AA7",
    "shape_pt_lon" : 21.082567000000012,
    "shape_pt_lat" : 44.325366000000002
  },
  {
    "shape_pt_sequence" : 518,
    "shape_id" : "1B223DB9-78C8-4A42-8F3E-62EC9CB60AA7",
    "shape_pt_lon" : 21.077750000000009,
    "shape_pt_lat" : 44.336962
  },
  {
    "shape_pt_sequence" : 519,
    "shape_id" : "1B223DB9-78C8-4A42-8F3E-62EC9CB60AA7",
    "shape_pt_lon" : 21.072156000000035,
    "shape_pt_lat" : 44.339150000000004
  },
  {
    "shape_pt_sequence" : 520,
    "shape_id" : "1B223DB9-78C8-4A42-8F3E-62EC9CB60AA7",
    "shape_pt_lon" : 21.052888999999993,
    "shape_pt_lat" : 44.338828000000007
  },
  {
    "shape_pt_sequence" : 521,
    "shape_id" : "1B223DB9-78C8-4A42-8F3E-62EC9CB60AA7",
    "shape_pt_lon" : 21.015327000000013,
    "shape_pt_lat" : 44.335884
  },
  {
    "shape_pt_sequence" : 522,
    "shape_id" : "1B223DB9-78C8-4A42-8F3E-62EC9CB60AA7",
    "shape_pt_lon" : 20.977011000000005,
    "shape_pt_lat" : 44.355392999999999
  },
  {
    "shape_pt_sequence" : 523,
    "shape_id" : "1B223DB9-78C8-4A42-8F3E-62EC9CB60AA7",
    "shape_pt_lon" : 20.954823000000005,
    "shape_pt_lat" : 44.364308000000001
  },
  {
    "shape_pt_sequence" : 524,
    "shape_id" : "1B223DB9-78C8-4A42-8F3E-62EC9CB60AA7",
    "shape_pt_lon" : 20.948671000000019,
    "shape_pt_lat" : 44.364088000000002
  },
  {
    "shape_pt_sequence" : 525,
    "shape_id" : "1B223DB9-78C8-4A42-8F3E-62EC9CB60AA7",
    "shape_pt_lon" : 20.912116999999995,
    "shape_pt_lat" : 44.369177000000001
  },
  {
    "shape_pt_sequence" : 526,
    "shape_id" : "1B223DB9-78C8-4A42-8F3E-62EC9CB60AA7",
    "shape_pt_lon" : 20.865214000000009,
    "shape_pt_lat" : 44.368268000000008
  },
  {
    "shape_pt_sequence" : 527,
    "shape_id" : "1B223DB9-78C8-4A42-8F3E-62EC9CB60AA7",
    "shape_pt_lon" : 20.843194000000011,
    "shape_pt_lat" : 44.377726999999993
  },
  {
    "shape_pt_sequence" : 528,
    "shape_id" : "1B223DB9-78C8-4A42-8F3E-62EC9CB60AA7",
    "shape_pt_lon" : 20.815767000000022,
    "shape_pt_lat" : 44.373574999999988
  },
  {
    "shape_pt_sequence" : 529,
    "shape_id" : "1B223DB9-78C8-4A42-8F3E-62EC9CB60AA7",
    "shape_pt_lon" : 20.781649000000044,
    "shape_pt_lat" : 44.384566999999997
  },
  {
    "shape_pt_sequence" : 530,
    "shape_id" : "1B223DB9-78C8-4A42-8F3E-62EC9CB60AA7",
    "shape_pt_lon" : 20.763746999999995,
    "shape_pt_lat" : 44.385689999999997
  },
  {
    "shape_pt_sequence" : 531,
    "shape_id" : "1B223DB9-78C8-4A42-8F3E-62EC9CB60AA7",
    "shape_pt_lon" : 20.755205999999987,
    "shape_pt_lat" : 44.397624
  },
  {
    "shape_pt_sequence" : 532,
    "shape_id" : "1B223DB9-78C8-4A42-8F3E-62EC9CB60AA7",
    "shape_pt_lon" : 20.741292999999956,
    "shape_pt_lat" : 44.402239000000002
  },
  {
    "shape_pt_sequence" : 533,
    "shape_id" : "1B223DB9-78C8-4A42-8F3E-62EC9CB60AA7",
    "shape_pt_lon" : 20.723865000000018,
    "shape_pt_lat" : 44.406638999999991
  },
  {
    "shape_pt_sequence" : 534,
    "shape_id" : "1B223DB9-78C8-4A42-8F3E-62EC9CB60AA7",
    "shape_pt_lon" : 20.697305999999998,
    "shape_pt_lat" : 44.428978999999991
  },
  {
    "shape_pt_sequence" : 535,
    "shape_id" : "1B223DB9-78C8-4A42-8F3E-62EC9CB60AA7",
    "shape_pt_lon" : 20.69133400000004,
    "shape_pt_lat" : 44.440249999999985
  },
  {
    "shape_pt_sequence" : 536,
    "shape_id" : "1B223DB9-78C8-4A42-8F3E-62EC9CB60AA7",
    "shape_pt_lon" : 20.69133400000004,
    "shape_pt_lat" : 44.440249999999985
  },
  {
    "shape_pt_sequence" : 537,
    "shape_id" : "1B223DB9-78C8-4A42-8F3E-62EC9CB60AA7",
    "shape_pt_lon" : 20.691361000000001,
    "shape_pt_lat" : 44.440260000000002
  },
  {
    "shape_pt_sequence" : 538,
    "shape_id" : "1B223DB9-78C8-4A42-8F3E-62EC9CB60AA7",
    "shape_pt_lon" : 20.465599999999998,
    "shape_pt_lat" : 44.802419999999998
  }
]